{
 "video_id": "FLKy7W2W9DM",
 "channel_id": "UCGsDIP_K6J6VSTqlq-9IPlg",
 "channel_name": "Paul VanderKlay",
 "title": "Crazy Rich Asians and Christianity",
 "url": "https://www.youtube.com/watch?v=FLKy7W2W9DM",
 "date": "2018-09-14",
 "description": "Crazy Rich Asians is a movie about the class of cultures. Is the traditional Chinese approach to marriage correct, or American Expressive Individualism? Obadiah prophesies the destruction of Edom. But what is Edom and Israel? By blood, belief or behavior? \n\nFor the audio podcast mirror on Podbean http://paulvanderklay.podbean.com/\n\nTo listen to this on ITunes https://itunes.apple.com/us/podcast/paul-vanderklays-podcast/id1394314333 \n\nIf you need the RSS feed for your podcast player https://paulvanderklay.podbean.com/feed/ \n\nTo support this channel/podcast on Patreon https://www.patreon.com/paulvanderklay\n\nJoin the Sacramento JBP Meetup https://www.meetup.com/Sacramento-Jordan-Peterson-Meetup/\n\nPaul's Church Content at Living Stones Channel https://www.youtube.com/channel/UCh7bdktIALZ9Nq41oVCvW-A\n\nYou can donate to Living Stones CRC to support this work here http://www.livingstonescrc.org/donate \nDonations may be tax deductible for taxpayers of the United States",
 "duration": 1431,
 "transcript_parts": [
  {
   "text": "hi this is Paul and this is rough draft",
   "start": 0.0,
   "duration": 3.84
  },
  {
   "text": "for Sunday where I run through that",
   "start": 2.34,
   "duration": 3.769
  },
  {
   "text": "current status of my Sunday sermon and",
   "start": 3.84,
   "duration": 5.429
  },
  {
   "text": "we start this week talking about crazy",
   "start": 6.109,
   "duration": 6.011
  },
  {
   "text": "rich Asians this is a very popular movie",
   "start": 9.269,
   "duration": 3.601
  },
  {
   "text": "right now",
   "start": 12.12,
   "duration": 3.9
  },
  {
   "text": "it's grossed 170 million worldwide and I",
   "start": 12.87,
   "duration": 4.919
  },
  {
   "text": "expect when it gets to China it look",
   "start": 16.02,
   "duration": 4.41
  },
  {
   "text": "gross even more they it's a very",
   "start": 17.789,
   "duration": 5.881
  },
  {
   "text": "traditional story of a rich guy and not",
   "start": 20.43,
   "duration": 5.759
  },
  {
   "text": "as rich girl she's not exactly poor but",
   "start": 23.67,
   "duration": 3.689
  },
  {
   "text": "what the story is really about is the",
   "start": 26.189,
   "duration": 3.42
  },
  {
   "text": "clash between eight American and Asian",
   "start": 27.359,
   "duration": 5.761
  },
  {
   "text": "cultures in terms of who to decide who",
   "start": 29.609,
   "duration": 6.811
  },
  {
   "text": "you marry and it's this is very",
   "start": 33.12,
   "duration": 4.95
  },
  {
   "text": "interesting because China's very big",
   "start": 36.42,
   "duration": 3.959
  },
  {
   "text": "country and there's still quite a bit of",
   "start": 38.07,
   "duration": 4.41
  },
  {
   "text": "tradition in China in fact it was just a",
   "start": 40.379,
   "duration": 4.801
  },
  {
   "text": "couple of years ago that my daughter's a",
   "start": 42.48,
   "duration": 4.95
  },
  {
   "text": "friend of a friend and the band of my",
   "start": 45.18,
   "duration": 4.26
  },
  {
   "text": "daughter's got married and my daughter",
   "start": 47.43,
   "duration": 4.289
  },
  {
   "text": "said yes she had an arranged marriage",
   "start": 49.44,
   "duration": 4.17
  },
  {
   "text": "and I thought well that's really",
   "start": 51.719,
   "duration": 4.471
  },
  {
   "text": "interesting this this girl graduating",
   "start": 53.61,
   "duration": 4.589
  },
  {
   "text": "high school here in Sacramento",
   "start": 56.19,
   "duration": 7.23
  },
  {
   "text": "California of Chinese descent marrying",
   "start": 58.199,
   "duration": 7.561
  },
  {
   "text": "the man that her parents arranged her to",
   "start": 63.42,
   "duration": 5.64
  },
  {
   "text": "marry now the the movie is really about",
   "start": 65.76,
   "duration": 5.609
  },
  {
   "text": "the conflict between expressive",
   "start": 69.06,
   "duration": 5.37
  },
  {
   "text": "individualism which is what Robert",
   "start": 71.369,
   "duration": 3.511
  },
  {
   "text": "Bellah",
   "start": 74.43,
   "duration": 3.81
  },
  {
   "text": "and habits of the heart called American",
   "start": 74.88,
   "duration": 6.18
  },
  {
   "text": "culture versus generational duty which",
   "start": 78.24,
   "duration": 4.47
  },
  {
   "text": "is something that traditional Chinese",
   "start": 81.06,
   "duration": 5.46
  },
  {
   "text": "culture values and so here this this",
   "start": 82.71,
   "duration": 6.479
  },
  {
   "text": "rich son of a of a huge vision this",
   "start": 86.52,
   "duration": 5.07
  },
  {
   "text": "Empire is expected to make a match",
   "start": 89.189,
   "duration": 5.911
  },
  {
   "text": "according to his status with a woman",
   "start": 91.59,
   "duration": 5.76
  },
  {
   "text": "that will give him additional business",
   "start": 95.1,
   "duration": 6.21
  },
  {
   "text": "or political ties and that's that's the",
   "start": 97.35,
   "duration": 6.089
  },
  {
   "text": "game that the parents and grandparents",
   "start": 101.31,
   "duration": 4.05
  },
  {
   "text": "are playing and here in this picture the",
   "start": 103.439,
   "duration": 4.021
  },
  {
   "text": "grandmother is is looking over this",
   "start": 105.36,
   "duration": 3.869
  },
  {
   "text": "woman and it doesn't matter that she has",
   "start": 107.46,
   "duration": 4.89
  },
  {
   "text": "a PhD and teaches teaches economics and",
   "start": 109.229,
   "duration": 5.43
  },
  {
   "text": "an American University she's not from",
   "start": 112.35,
   "duration": 5.19
  },
  {
   "text": "the right family and and so you have",
   "start": 114.659,
   "duration": 6.03
  },
  {
   "text": "this this conflict set up and of course",
   "start": 117.54,
   "duration": 5.039
  },
  {
   "text": "the threat is that if the son doesn't",
   "start": 120.689,
   "duration": 3.901
  },
  {
   "text": "marry the right girl the family will",
   "start": 122.579,
   "duration": 5.25
  },
  {
   "text": "disinherit him and he won't inherit any",
   "start": 124.59,
   "duration": 6.059
  },
  {
   "text": "of this money and and what this what",
   "start": 127.829,
   "duration": 6.091
  },
  {
   "text": "gets set up that is this is this idea",
   "start": 130.649,
   "duration": 5.521
  },
  {
   "text": "conflict between what makes me happy now",
   "start": 133.92,
   "duration": 5.01
  },
  {
   "text": "versus family well-being for a hundred",
   "start": 136.17,
   "duration": 4.8
  },
  {
   "text": "years from now and I'm sure it wouldn't",
   "start": 138.93,
   "duration": 4.919
  },
  {
   "text": "feel real great to have someone say yeah",
   "start": 140.97,
   "duration": 4.68
  },
  {
   "text": "grandpa gave up his fortune to marry",
   "start": 143.849,
   "duration": 3.511
  },
  {
   "text": "grandma because she was young and hot",
   "start": 145.65,
   "duration": 5.97
  },
  {
   "text": "and now I get to drive this these",
   "start": 147.36,
   "duration": 6.78
  },
  {
   "text": "questions often have a dimension of time",
   "start": 151.62,
   "duration": 5.55
  },
  {
   "text": "in them and and we wonder well how to",
   "start": 154.14,
   "duration": 5.58
  },
  {
   "text": "make the best decision is this is this",
   "start": 157.17,
   "duration": 5.3
  },
  {
   "text": "Chinese practice of intergenerational",
   "start": 159.72,
   "duration": 6.48
  },
  {
   "text": "planning should the should the son",
   "start": 162.47,
   "duration": 6.18
  },
  {
   "text": "submit to the family well-being",
   "start": 166.2,
   "duration": 6.08
  },
  {
   "text": "generationally or does however he feels",
   "start": 168.65,
   "duration": 6.7
  },
  {
   "text": "whoever he feels he wants to be with for",
   "start": 172.28,
   "duration": 5.32
  },
  {
   "text": "his life I mean this is America this is",
   "start": 175.35,
   "duration": 4.62
  },
  {
   "text": "expressive individualism and the",
   "start": 177.6,
   "duration": 5.1
  },
  {
   "text": "goodness of the now versus the family",
   "start": 179.97,
   "duration": 4.62
  },
  {
   "text": "duty for generations to come",
   "start": 182.7,
   "duration": 4.349
  },
  {
   "text": "and and what gets elevated in the movie",
   "start": 184.59,
   "duration": 3.66
  },
  {
   "text": "is the question is this girl",
   "start": 187.049,
   "duration": 3.72
  },
  {
   "text": "sufficiently Chinese and then so that",
   "start": 188.25,
   "duration": 4.2
  },
  {
   "text": "asks that raises the question what does",
   "start": 190.769,
   "duration": 3.991
  },
  {
   "text": "it mean to be Chinese",
   "start": 192.45,
   "duration": 4.59
  },
  {
   "text": "is it enough to have a Chinese passport",
   "start": 194.76,
   "duration": 4.349
  },
  {
   "text": "does that make you Chinese a while ago I",
   "start": 197.04,
   "duration": 3.72
  },
  {
   "text": "read an interesting article I think it",
   "start": 199.109,
   "duration": 3.961
  },
  {
   "text": "was an economist on the relationship",
   "start": 200.76,
   "duration": 4.17
  },
  {
   "text": "between being Chinese and being Han",
   "start": 203.07,
   "duration": 3.78
  },
  {
   "text": "which is a particular ethnic group",
   "start": 204.93,
   "duration": 5.22
  },
  {
   "text": "within China the physical features that",
   "start": 206.85,
   "duration": 5.31
  },
  {
   "text": "match the profile the granel was sitting",
   "start": 210.15,
   "duration": 3.6
  },
  {
   "text": "there looking at her nose it said oh you",
   "start": 212.16,
   "duration": 3.54
  },
  {
   "text": "have a nice nose born to the right",
   "start": 213.75,
   "duration": 4.14
  },
  {
   "text": "family do you have money now early on in",
   "start": 215.7,
   "duration": 5.069
  },
  {
   "text": "the movie Rachel Chu who is the female",
   "start": 217.89,
   "duration": 6.99
  },
  {
   "text": "protagonist is said that the mother of",
   "start": 220.769,
   "duration": 6.03
  },
  {
   "text": "the the mother of the son says you're",
   "start": 224.88,
   "duration": 4.53
  },
  {
   "text": "not Chinese you're chinese-american",
   "start": 226.799,
   "duration": 5.581
  },
  {
   "text": "and and and Rachel chews mother had told",
   "start": 229.41,
   "duration": 5.549
  },
  {
   "text": "her as she said well you're Chinese here",
   "start": 232.38,
   "duration": 5.28
  },
  {
   "text": "in terms of on the outside but you're",
   "start": 234.959,
   "duration": 5.911
  },
  {
   "text": "not Chinese in here in the heart and in",
   "start": 237.66,
   "duration": 5.34
  },
  {
   "text": "fact the plot of the whole movie focuses",
   "start": 240.87,
   "duration": 5.399
  },
  {
   "text": "around is she sufficiently Chinese does",
   "start": 243.0,
   "duration": 5.88
  },
  {
   "text": "she need to be Chinese to marry what's",
   "start": 246.269,
   "duration": 5.491
  },
  {
   "text": "the proper norm what's the proper goal",
   "start": 248.88,
   "duration": 5.939
  },
  {
   "text": "what's the truth is it the wealthy",
   "start": 251.76,
   "duration": 4.71
  },
  {
   "text": "families multi generation business",
   "start": 254.819,
   "duration": 3.781
  },
  {
   "text": "interests that are most important in a",
   "start": 256.47,
   "duration": 5.22
  },
  {
   "text": "match like this or is it the feelings",
   "start": 258.6,
   "duration": 6.629
  },
  {
   "text": "that the couple has and this also boils",
   "start": 261.69,
   "duration": 4.8
  },
  {
   "text": "down to the question then what is",
   "start": 265.229,
   "duration": 2.581
  },
  {
   "text": "marriage",
   "start": 266.49,
   "duration": 3.179
  },
  {
   "text": "contemporary American MANET marriage is",
   "start": 267.81,
   "duration": 3.81
  },
  {
   "text": "all about expressive individualism an",
   "start": 269.669,
   "duration": 3.961
  },
  {
   "text": "expressive internal emotional state",
   "start": 271.62,
   "duration": 5.4
  },
  {
   "text": "being in love you make me happy this is",
   "start": 273.63,
   "duration": 5.97
  },
  {
   "text": "the criteria for marriage in America but",
   "start": 277.02,
   "duration": 4.17
  },
  {
   "text": "traditional marriage pretty much around",
   "start": 279.6,
   "duration": 5.16
  },
  {
   "text": "the world was was for a specific goal",
   "start": 281.19,
   "duration": 6.06
  },
  {
   "text": "and it was you know often in places in",
   "start": 284.76,
   "duration": 4.35
  },
  {
   "text": "the world well you could have mistresses",
   "start": 287.25,
   "duration": 4.11
  },
  {
   "text": "and concubines and flings and yeah",
   "start": 289.11,
   "duration": 4.2
  },
  {
   "text": "everybody understood the you know the",
   "start": 291.36,
   "duration": 3.84
  },
  {
   "text": "needs of the heart but marriage was",
   "start": 293.31,
   "duration": 4.35
  },
  {
   "text": "about money and heirs and family and and",
   "start": 295.2,
   "duration": 4.95
  },
  {
   "text": "business and politics and all of those",
   "start": 297.66,
   "duration": 4.53
  },
  {
   "text": "things which lasts considerably longer",
   "start": 300.15,
   "duration": 4.11
  },
  {
   "text": "than one's feelings towards a person of",
   "start": 302.19,
   "duration": 5.039
  },
  {
   "text": "of the opposite sex it was how to create",
   "start": 304.26,
   "duration": 4.98
  },
  {
   "text": "a family out of someone without a blood",
   "start": 307.229,
   "duration": 5.761
  },
  {
   "text": "tie and often in some cases like Abraham",
   "start": 309.24,
   "duration": 5.399
  },
  {
   "text": "marrying his half-sister often there was",
   "start": 312.99,
   "duration": 3.54
  },
  {
   "text": "one of those two he wanted to marry",
   "start": 314.639,
   "duration": 3.571
  },
  {
   "text": "someone within the family but not two",
   "start": 316.53,
   "duration": 4.56
  },
  {
   "text": "foot not too close in the family and and",
   "start": 318.21,
   "duration": 4.23
  },
  {
   "text": "these were this was a multi-generational",
   "start": 321.09,
   "duration": 3.36
  },
  {
   "text": "pop project and people were planning",
   "start": 322.44,
   "duration": 4.46
  },
  {
   "text": "three four or five generations ahead",
   "start": 324.45,
   "duration": 4.98
  },
  {
   "text": "Americans tend to like to live in the",
   "start": 326.9,
   "duration": 5.68
  },
  {
   "text": "now now if you read the Bible you begin",
   "start": 329.43,
   "duration": 5.04
  },
  {
   "text": "to notice that the Bible is a very",
   "start": 332.58,
   "duration": 3.81
  },
  {
   "text": "traditional book and the Bible's pays",
   "start": 334.47,
   "duration": 4.74
  },
  {
   "text": "very close attention to these blood tie",
   "start": 336.39,
   "duration": 6.06
  },
  {
   "text": "things in fact in after the flood you",
   "start": 339.21,
   "duration": 5.91
  },
  {
   "text": "have Noah and that the table of the",
   "start": 342.45,
   "duration": 4.17
  },
  {
   "text": "nations as it's called in the book of",
   "start": 345.12,
   "duration": 3.54
  },
  {
   "text": "Genesis and you have Shem ham and",
   "start": 346.62,
   "duration": 4.32
  },
  {
   "text": "Japheth and the descendants of ham are",
   "start": 348.66,
   "duration": 5.009
  },
  {
   "text": "those in Egypt and cush and Canaan the",
   "start": 350.94,
   "duration": 4.8
  },
  {
   "text": "descendants of Shem are those north of",
   "start": 353.669,
   "duration": 4.591
  },
  {
   "text": "Canaan and Mesopotamia and the Fertile",
   "start": 355.74,
   "duration": 5.07
  },
  {
   "text": "Crescent and just descendants of Japheth",
   "start": 358.26,
   "duration": 4.68
  },
  {
   "text": "er are a bit further away and so they",
   "start": 360.81,
   "duration": 3.84
  },
  {
   "text": "don't come into the story much and then",
   "start": 362.94,
   "duration": 3.33
  },
  {
   "text": "you have Abraham who was the father of",
   "start": 364.65,
   "duration": 4.8
  },
  {
   "text": "the nations and his nephew who he brings",
   "start": 366.27,
   "duration": 6.36
  },
  {
   "text": "into Canaan where he leaves her is lot",
   "start": 369.45,
   "duration": 5.79
  },
  {
   "text": "and lots two sons that he had via his",
   "start": 372.63,
   "duration": 5.58
  },
  {
   "text": "daughters in the cave outside Sodom were",
   "start": 375.24,
   "duration": 6.57
  },
  {
   "text": "Moab and ben-ami who is the father of",
   "start": 378.21,
   "duration": 7.11
  },
  {
   "text": "Ammon and if you look at a map of the 12",
   "start": 381.81,
   "duration": 5.55
  },
  {
   "text": "tribes of Israel you can see them there",
   "start": 385.32,
   "duration": 6.719
  },
  {
   "text": "and so you see Edom and then Abraham's",
   "start": 387.36,
   "duration": 8.34
  },
  {
   "text": "son Isaac has two sons Jacob and Esau",
   "start": 392.039,
   "duration": 6.63
  },
  {
   "text": "and there again you can see Jacob who's",
   "start": 395.7,
   "duration": 5.73
  },
  {
   "text": "twelve tribes become Israel and they",
   "start": 398.669,
   "duration": 5.34
  },
  {
   "text": "throughout the region and you have Esau",
   "start": 401.43,
   "duration": 5.43
  },
  {
   "text": "who is Edom now one of the things that",
   "start": 404.009,
   "duration": 6.901
  },
  {
   "text": "we Americans don't pay much attention to",
   "start": 406.86,
   "duration": 6.69
  },
  {
   "text": "that the Chinese are paying attention to",
   "start": 410.91,
   "duration": 5.19
  },
  {
   "text": "the Hebrews are paying attention to",
   "start": 413.55,
   "duration": 4.26
  },
  {
   "text": "traditional people throughout human",
   "start": 416.1,
   "duration": 3.659
  },
  {
   "text": "history have paid attention to is the",
   "start": 417.81,
   "duration": 3.96
  },
  {
   "text": "relationship between individuals and",
   "start": 419.759,
   "duration": 4.261
  },
  {
   "text": "peoples in fact in Plato's Republic",
   "start": 421.77,
   "duration": 4.05
  },
  {
   "text": "which is one of the most important books",
   "start": 424.02,
   "duration": 5.119
  },
  {
   "text": "and and all of in all of human history",
   "start": 425.82,
   "duration": 6.33
  },
  {
   "text": "the entire book revolves around in many",
   "start": 429.139,
   "duration": 5.201
  },
  {
   "text": "ways it's about justice and",
   "start": 432.15,
   "duration": 3.66
  },
  {
   "text": "righteousness because this word that",
   "start": 434.34,
   "duration": 3.72
  },
  {
   "text": "they uses is for both justice and",
   "start": 435.81,
   "duration": 7.169
  },
  {
   "text": "righteousness but it's Plato is is our",
   "start": 438.06,
   "duration": 7.139
  },
  {
   "text": "Socrates as having these dialogues with",
   "start": 442.979,
   "duration": 3.841
  },
  {
   "text": "people these debates with people and",
   "start": 445.199,
   "duration": 3.361
  },
  {
   "text": "he's saying well to find justice and",
   "start": 446.82,
   "duration": 4.05
  },
  {
   "text": "individuals is too hard so let's blow up",
   "start": 448.56,
   "duration": 4.77
  },
  {
   "text": "the individual to the level of the city",
   "start": 450.87,
   "duration": 6.0
  },
  {
   "text": "and and maybe because a city is bigger",
   "start": 453.33,
   "duration": 5.13
  },
  {
   "text": "than an individual we can see what",
   "start": 456.87,
   "duration": 3.96
  },
  {
   "text": "justice is by looking at the city so",
   "start": 458.46,
   "duration": 5.22
  },
  {
   "text": "then Socrates and the and the brothers",
   "start": 460.83,
   "duration": 5.13
  },
  {
   "text": "of the brothers of Plato talked about",
   "start": 463.68,
   "duration": 5.07
  },
  {
   "text": "you know what the just city would be so",
   "start": 465.96,
   "duration": 4.92
  },
  {
   "text": "that they could discover what justice is",
   "start": 468.75,
   "duration": 5.099
  },
  {
   "text": "an individual is too small so so you",
   "start": 470.88,
   "duration": 4.74
  },
  {
   "text": "need to look at the city and what the",
   "start": 473.849,
   "duration": 4.281
  },
  {
   "text": "city is is in many ways the the",
   "start": 475.62,
   "duration": 5.729
  },
  {
   "text": "magnification of the individual and the",
   "start": 478.13,
   "duration": 6.039
  },
  {
   "text": "city takes on the the culture of the",
   "start": 481.349,
   "duration": 4.711
  },
  {
   "text": "individual and in fact in the ancient",
   "start": 484.169,
   "duration": 4.171
  },
  {
   "text": "world cities would take on the names of",
   "start": 486.06,
   "duration": 4.109
  },
  {
   "text": "the gods who were the patrons of the",
   "start": 488.34,
   "duration": 4.259
  },
  {
   "text": "individual or the political gods that",
   "start": 490.169,
   "duration": 5.821
  },
  {
   "text": "founded them and Alexandria was founded",
   "start": 492.599,
   "duration": 5.911
  },
  {
   "text": "by Alexander Antioch was founded by",
   "start": 495.99,
   "duration": 4.919
  },
  {
   "text": "Antiochus and so this relationship",
   "start": 498.51,
   "duration": 4.17
  },
  {
   "text": "between the individual and the communal",
   "start": 500.909,
   "duration": 3.901
  },
  {
   "text": "or the nation or the city is something",
   "start": 502.68,
   "duration": 4.47
  },
  {
   "text": "that is that is built into the ancient",
   "start": 504.81,
   "duration": 7.169
  },
  {
   "text": "world now what happens to happen then",
   "start": 507.15,
   "duration": 6.6
  },
  {
   "text": "long term is the question well who was a",
   "start": 511.979,
   "duration": 5.071
  },
  {
   "text": "true son of Israel who is a true who is",
   "start": 513.75,
   "duration": 5.7
  },
  {
   "text": "a true member of this community",
   "start": 517.05,
   "duration": 5.58
  },
  {
   "text": "Israel is the younger son chosen by God",
   "start": 519.45,
   "duration": 6.03
  },
  {
   "text": "to rule the older siblings and we see",
   "start": 522.63,
   "duration": 5.579
  },
  {
   "text": "that in the stories of the Old Testament",
   "start": 525.48,
   "duration": 4.68
  },
  {
   "text": "it comes through again and again and",
   "start": 528.209,
   "duration": 5.211
  },
  {
   "text": "again and well this",
   "start": 530.16,
   "duration": 5.419
  },
  {
   "text": "this is heard in different ways and it's",
   "start": 533.42,
   "duration": 4.5
  },
  {
   "text": "and here's the thing when we listen to",
   "start": 535.579,
   "duration": 5.07
  },
  {
   "text": "this as Americans we evaluate it with",
   "start": 537.92,
   "duration": 5.609
  },
  {
   "text": "American ears we evaluate it within the",
   "start": 540.649,
   "duration": 4.981
  },
  {
   "text": "framework of the value system of our",
   "start": 543.529,
   "duration": 5.011
  },
  {
   "text": "culture well is that value system right",
   "start": 545.63,
   "duration": 4.41
  },
  {
   "text": "now obviously people from different",
   "start": 548.54,
   "duration": 3.359
  },
  {
   "text": "cultures have different value systems",
   "start": 550.04,
   "duration": 4.68
  },
  {
   "text": "and so when we hear the idea that that",
   "start": 551.899,
   "duration": 6.0
  },
  {
   "text": "Israel was to rule over her neighbors",
   "start": 554.72,
   "duration": 5.79
  },
  {
   "text": "well this is really an extension of the",
   "start": 557.899,
   "duration": 5.851
  },
  {
   "text": "story of Joseph ruling over his brothers",
   "start": 560.51,
   "duration": 7.259
  },
  {
   "text": "and then Jacob ruling over Esau and all",
   "start": 563.75,
   "duration": 6.42
  },
  {
   "text": "of this stuff is built into the Genesis",
   "start": 567.769,
   "duration": 4.411
  },
  {
   "text": "stories and so if you keep this in mind",
   "start": 570.17,
   "duration": 3.63
  },
  {
   "text": "when you listen to the Genesis stories",
   "start": 572.18,
   "duration": 4.23
  },
  {
   "text": "you'll you'll hear these themes begin to",
   "start": 573.8,
   "duration": 7.92
  },
  {
   "text": "develop now the book of Obadiah is it's",
   "start": 576.41,
   "duration": 7.08
  },
  {
   "text": "debated in terms of the date of the book",
   "start": 581.72,
   "duration": 3.929
  },
  {
   "text": "but many scholars believe it the book is",
   "start": 583.49,
   "duration": 4.74
  },
  {
   "text": "the book is addressing the period after",
   "start": 585.649,
   "duration": 4.5
  },
  {
   "text": "the destruction of Jerusalem by the",
   "start": 588.23,
   "duration": 4.56
  },
  {
   "text": "Babylonians and this is how the book",
   "start": 590.149,
   "duration": 5.43
  },
  {
   "text": "starts the vision of Obadiah this is",
   "start": 592.79,
   "duration": 4.979
  },
  {
   "text": "what the sovereign Lord says about Edom",
   "start": 595.579,
   "duration": 4.38
  },
  {
   "text": "we have heard a message from the Lord an",
   "start": 597.769,
   "duration": 4.5
  },
  {
   "text": "envoy was sent to the nation's to say",
   "start": 599.959,
   "duration": 4.831
  },
  {
   "text": "rise let us go against her for battle",
   "start": 602.269,
   "duration": 5.01
  },
  {
   "text": "see I will make you small among the",
   "start": 604.79,
   "duration": 5.58
  },
  {
   "text": "nations you will be utterly despised the",
   "start": 607.279,
   "duration": 5.25
  },
  {
   "text": "pride of your heart has deceived you you",
   "start": 610.37,
   "duration": 4.14
  },
  {
   "text": "who live in the clefts of the rocks and",
   "start": 612.529,
   "duration": 3.87
  },
  {
   "text": "make your home on the heights you who",
   "start": 614.51,
   "duration": 4.259
  },
  {
   "text": "say to yourself who can bring me down to",
   "start": 616.399,
   "duration": 4.291
  },
  {
   "text": "the ground though you soar like the",
   "start": 618.769,
   "duration": 4.26
  },
  {
   "text": "Eagle and make your nest among the stars",
   "start": 620.69,
   "duration": 4.98
  },
  {
   "text": "from where i from there I will bring you",
   "start": 623.029,
   "duration": 6.361
  },
  {
   "text": "down declares the Lord on in that day",
   "start": 625.67,
   "duration": 6.15
  },
  {
   "text": "declares the Lord I will not destroy the",
   "start": 629.39,
   "duration": 4.949
  },
  {
   "text": "wise will I not destroy the wise men of",
   "start": 631.82,
   "duration": 4.53
  },
  {
   "text": "Edom those of understanding in the",
   "start": 634.339,
   "duration": 4.711
  },
  {
   "text": "mountains of Esau you warriors teman",
   "start": 636.35,
   "duration": 5.37
  },
  {
   "text": "will be terrified and everyone in Esau's",
   "start": 639.05,
   "duration": 5.49
  },
  {
   "text": "mountains will be cut down in slaughter",
   "start": 641.72,
   "duration": 5.46
  },
  {
   "text": "and again this is a this is a type of",
   "start": 644.54,
   "duration": 5.45
  },
  {
   "text": "book that really offends and annoys",
   "start": 647.18,
   "duration": 6.779
  },
  {
   "text": "Americans and our sensitivities but now",
   "start": 649.99,
   "duration": 5.68
  },
  {
   "text": "pay attention to the family ties in the",
   "start": 653.959,
   "duration": 3.961
  },
  {
   "text": "book because of the violence against",
   "start": 655.67,
   "duration": 5.13
  },
  {
   "text": "your brother Jacob you will be covered",
   "start": 657.92,
   "duration": 5.97
  },
  {
   "text": "with shame you will be destroyed forever",
   "start": 660.8,
   "duration": 6.75
  },
  {
   "text": "you hear in this the assertion that well",
   "start": 663.89,
   "duration": 6.21
  },
  {
   "text": "is a family assertion that you know here",
   "start": 667.55,
   "duration": 4.44
  },
  {
   "text": "within the family we might fight like",
   "start": 670.1,
   "duration": 3.75
  },
  {
   "text": "cats and dogs but if someone's gonna",
   "start": 671.99,
   "duration": 3.93
  },
  {
   "text": "come from outside the family and fight",
   "start": 673.85,
   "duration": 4.26
  },
  {
   "text": "us well that's a whole different story",
   "start": 675.92,
   "duration": 4.71
  },
  {
   "text": "and so the message under this was that",
   "start": 678.11,
   "duration": 5.37
  },
  {
   "text": "when when Babylon came down and",
   "start": 680.63,
   "duration": 4.709
  },
  {
   "text": "destroyed the temple and destroyed",
   "start": 683.48,
   "duration": 5.52
  },
  {
   "text": "Jerusalem it was Edom Shree sponsibility",
   "start": 685.339,
   "duration": 7.531
  },
  {
   "text": "as a family member to stand with Israel",
   "start": 689.0,
   "duration": 6.87
  },
  {
   "text": "and she didn't now someone could say",
   "start": 692.87,
   "duration": 5.219
  },
  {
   "text": "yeah but Israel had dominated Edom and",
   "start": 695.87,
   "duration": 4.11
  },
  {
   "text": "Edom had dominated it you know there",
   "start": 698.089,
   "duration": 4.141
  },
  {
   "text": "were there were long-standing tensions",
   "start": 699.98,
   "duration": 4.53
  },
  {
   "text": "within the family but in a sense what is",
   "start": 702.23,
   "duration": 4.62
  },
  {
   "text": "what has reinforced or at least assumed",
   "start": 704.51,
   "duration": 4.769
  },
  {
   "text": "in here is a certain amount of family",
   "start": 706.85,
   "duration": 5.429
  },
  {
   "text": "loyalty and the this loyalty would be",
   "start": 709.279,
   "duration": 6.151
  },
  {
   "text": "built into the relationships between the",
   "start": 712.279,
   "duration": 7.171
  },
  {
   "text": "nations on that day now every time you",
   "start": 715.43,
   "duration": 6.3
  },
  {
   "text": "read on that day you have to get a sense",
   "start": 719.45,
   "duration": 3.99
  },
  {
   "text": "of this theme and the Old Testament",
   "start": 721.73,
   "duration": 3.06
  },
  {
   "text": "called the day of the Lord which you can",
   "start": 723.44,
   "duration": 3.0
  },
  {
   "text": "find in the book of Joel and you can",
   "start": 724.79,
   "duration": 3.72
  },
  {
   "text": "find another and and some of the other",
   "start": 726.44,
   "duration": 5.1
  },
  {
   "text": "prophetic messages on that day you stood",
   "start": 728.51,
   "duration": 5.76
  },
  {
   "text": "aloof while strangers carried off his",
   "start": 731.54,
   "duration": 5.16
  },
  {
   "text": "wealth and foreigners entered his gates",
   "start": 734.27,
   "duration": 5.25
  },
  {
   "text": "and cast lots for Jerusalem you were",
   "start": 736.7,
   "duration": 5.16
  },
  {
   "text": "like one of them in other words you",
   "start": 739.52,
   "duration": 6.27
  },
  {
   "text": "didn't uphold the family ties you should",
   "start": 741.86,
   "duration": 5.91
  },
  {
   "text": "not gloat over your brother in the day",
   "start": 745.79,
   "duration": 4.89
  },
  {
   "text": "of his misfortune nor rejoice over the",
   "start": 747.77,
   "duration": 4.68
  },
  {
   "text": "people of Judah and the day of their",
   "start": 750.68,
   "duration": 4.38
  },
  {
   "text": "destruction nor boast so much in the day",
   "start": 752.45,
   "duration": 5.87
  },
  {
   "text": "of their trouble you should not march",
   "start": 755.06,
   "duration": 5.88
  },
  {
   "text": "through the gates of my people on the",
   "start": 758.32,
   "duration": 4.78
  },
  {
   "text": "day of their disaster nor gloat over",
   "start": 760.94,
   "duration": 3.99
  },
  {
   "text": "them and their calamity in the day of",
   "start": 763.1,
   "duration": 4.08
  },
  {
   "text": "their disaster nor seize their wealth in",
   "start": 764.93,
   "duration": 4.98
  },
  {
   "text": "the day of the disaster the story goes",
   "start": 767.18,
   "duration": 4.68
  },
  {
   "text": "that the on the heels of the",
   "start": 769.91,
   "duration": 4.169
  },
  {
   "text": "Babylonians came in and finished the",
   "start": 771.86,
   "duration": 5.12
  },
  {
   "text": "looting that the Babylonians had started",
   "start": 774.079,
   "duration": 5.57
  },
  {
   "text": "until here the Lord says to eat them",
   "start": 776.98,
   "duration": 5.44
  },
  {
   "text": "you're going to pay for that and I'm",
   "start": 779.649,
   "duration": 5.05
  },
  {
   "text": "going to destroy you because of that",
   "start": 782.42,
   "duration": 4.44
  },
  {
   "text": "and again this triggers us we say well",
   "start": 784.699,
   "duration": 3.841
  },
  {
   "text": "God shouldn't pick and choose god",
   "start": 786.86,
   "duration": 4.44
  },
  {
   "text": "shouldn't act god shouldn't behave this",
   "start": 788.54,
   "duration": 5.25
  },
  {
   "text": "way certainly God shouldn't play",
   "start": 791.3,
   "duration": 4.62
  },
  {
   "text": "favorites among the nations God should",
   "start": 793.79,
   "duration": 5.549
  },
  {
   "text": "transcend all of that you should not",
   "start": 795.92,
   "duration": 5.43
  },
  {
   "text": "wait at the crossroads to cut",
   "start": 799.339,
   "duration": 4.921
  },
  {
   "text": "down there fugitives nor hand over there",
   "start": 801.35,
   "duration": 5.46
  },
  {
   "text": "survivals in the day of their trouble",
   "start": 804.26,
   "duration": 5.01
  },
  {
   "text": "the day of the Lord is near for all",
   "start": 806.81,
   "duration": 3.81
  },
  {
   "text": "nations what does that mean that's",
   "start": 809.27,
   "duration": 4.2
  },
  {
   "text": "Judgment Day the day of the Lord is near",
   "start": 810.62,
   "duration": 4.68
  },
  {
   "text": "for all nations and see Judgment Day",
   "start": 813.47,
   "duration": 4.47
  },
  {
   "text": "isn't just one days it's it's many days",
   "start": 815.3,
   "duration": 5.43
  },
  {
   "text": "the day of the Lord comes like a pre",
   "start": 817.94,
   "duration": 6.24
  },
  {
   "text": "echo it comes and the final day of the",
   "start": 820.73,
   "duration": 5.61
  },
  {
   "text": "Lord is coming but but often in the",
   "start": 824.18,
   "duration": 4.62
  },
  {
   "text": "Bible we are pulled into the future by",
   "start": 826.34,
   "duration": 5.49
  },
  {
   "text": "the future by its gravitational force",
   "start": 828.8,
   "duration": 6.36
  },
  {
   "text": "the the end pulls the now in the Bible",
   "start": 831.83,
   "duration": 5.37
  },
  {
   "text": "and and so in a sense the day of the",
   "start": 835.16,
   "duration": 3.36
  },
  {
   "text": "Lord this is the these are the",
   "start": 837.2,
   "duration": 3.54
  },
  {
   "text": "firstfruits the harbingers of the day of",
   "start": 838.52,
   "duration": 4.29
  },
  {
   "text": "the Lord and Edom is going to face",
   "start": 840.74,
   "duration": 4.53
  },
  {
   "text": "judgment for the sins that she did",
   "start": 842.81,
   "duration": 6.12
  },
  {
   "text": "against her brother Jacob as you have",
   "start": 845.27,
   "duration": 5.76
  },
  {
   "text": "done it will be done to you your deeds",
   "start": 848.93,
   "duration": 4.95
  },
  {
   "text": "will return on your own head just as you",
   "start": 851.03,
   "duration": 5.94
  },
  {
   "text": "drank on my holy hill so all the nations",
   "start": 853.88,
   "duration": 5.4
  },
  {
   "text": "will drink continually they will drink",
   "start": 856.97,
   "duration": 4.92
  },
  {
   "text": "and drink and be as if they had never",
   "start": 859.28,
   "duration": 4.92
  },
  {
   "text": "been drink of what drink of the wrath",
   "start": 861.89,
   "duration": 4.47
  },
  {
   "text": "drink of their destruction they are",
   "start": 864.2,
   "duration": 5.52
  },
  {
   "text": "drinking to their own destruction but on",
   "start": 866.36,
   "duration": 6.0
  },
  {
   "text": "Mount Zion Mount Zion will be",
   "start": 869.72,
   "duration": 6.63
  },
  {
   "text": "deliverance it will be holy and Jacob",
   "start": 872.36,
   "duration": 6.3
  },
  {
   "text": "will possess his inheritance back to",
   "start": 876.35,
   "duration": 5.33
  },
  {
   "text": "this theme of Jacob ruling the nations",
   "start": 878.66,
   "duration": 6.26
  },
  {
   "text": "Jacob will be a fire and Joseph a flame",
   "start": 881.68,
   "duration": 6.55
  },
  {
   "text": "Esau will be stubble and they will be",
   "start": 884.92,
   "duration": 6.1
  },
  {
   "text": "set on fire and destroy him there will",
   "start": 888.23,
   "duration": 5.58
  },
  {
   "text": "be no survivors for Esau the Lord has",
   "start": 891.02,
   "duration": 5.76
  },
  {
   "text": "spoken now again a number of people will",
   "start": 893.81,
   "duration": 4.59
  },
  {
   "text": "read this and say well this is exactly",
   "start": 896.78,
   "duration": 2.94
  },
  {
   "text": "what we expect to find in the Old",
   "start": 898.4,
   "duration": 3.51
  },
  {
   "text": "Testament this is this is Hebrew",
   "start": 899.72,
   "duration": 4.53
  },
  {
   "text": "nationalism expressing itself in poetry",
   "start": 901.91,
   "duration": 5.88
  },
  {
   "text": "and every nation did this Edom and had",
   "start": 904.25,
   "duration": 6.18
  },
  {
   "text": "poems that imagine their own supremacy",
   "start": 907.79,
   "duration": 6.3
  },
  {
   "text": "over its neighbors Moab did Babylon did",
   "start": 910.43,
   "duration": 7.25
  },
  {
   "text": "Egypt did this is just what nations do",
   "start": 914.09,
   "duration": 10.62
  },
  {
   "text": "okay but it came true Edom was destroyed",
   "start": 917.68,
   "duration": 10.12
  },
  {
   "text": "in fact today people flocked to see the",
   "start": 924.71,
   "duration": 4.74
  },
  {
   "text": "ruins of Petra and they think oh look",
   "start": 927.8,
   "duration": 3.75
  },
  {
   "text": "Edom it wasn't Edom that were the",
   "start": 929.45,
   "duration": 4.02
  },
  {
   "text": "Nabataeans and they were from Arabia",
   "start": 931.55,
   "duration": 3.16
  },
  {
   "text": "they were the Conqueror",
   "start": 933.47,
   "duration": 4.33
  },
  {
   "text": "of edom they came in and supplanted the",
   "start": 934.71,
   "duration": 5.85
  },
  {
   "text": " and they built a prosperous",
   "start": 937.8,
   "duration": 5.49
  },
  {
   "text": "thriving nation there that too had its",
   "start": 940.56,
   "duration": 6.0
  },
  {
   "text": "day and fell they invaded and replaced",
   "start": 943.29,
   "duration": 5.01
  },
  {
   "text": "the and their culture in fact",
   "start": 946.56,
   "duration": 4.5
  },
  {
   "text": "Herod the Great had Edomite blood but",
   "start": 948.3,
   "duration": 5.25
  },
  {
   "text": "the were no longer much of an",
   "start": 951.06,
   "duration": 4.59
  },
  {
   "text": "effective people just like the",
   "start": 953.55,
   "duration": 4.38
  },
  {
   "text": "Nabataeans are no longer an effective",
   "start": 955.65,
   "duration": 5.37
  },
  {
   "text": "people so so the day of the Lord comes",
   "start": 957.93,
   "duration": 5.28
  },
  {
   "text": "and the day of the Lord destroys and",
   "start": 961.02,
   "duration": 3.69
  },
  {
   "text": "again as we said last week people say",
   "start": 963.21,
   "duration": 4.26
  },
  {
   "text": "yeah but every nation every Empire Falls",
   "start": 964.71,
   "duration": 5.37
  },
  {
   "text": "and when we say that we should think",
   "start": 967.47,
   "duration": 3.48
  },
  {
   "text": "yeah",
   "start": 970.08,
   "duration": 3.39
  },
  {
   "text": "every Empire Falls and then we think",
   "start": 970.95,
   "duration": 4.08
  },
  {
   "text": "well I hope it doesn't fall",
   "start": 973.47,
   "duration": 4.83
  },
  {
   "text": "I hope my empire doesn't fall when I'm",
   "start": 975.03,
   "duration": 5.18
  },
  {
   "text": "around",
   "start": 978.3,
   "duration": 6.21
  },
  {
   "text": "but Obadiah doesn't stop there people of",
   "start": 980.21,
   "duration": 6.88
  },
  {
   "text": "the Negev will occupy the mountains of",
   "start": 984.51,
   "duration": 5.31
  },
  {
   "text": "Esau and people from the foothills will",
   "start": 987.09,
   "duration": 5.1
  },
  {
   "text": "possess the land of the Philistines they",
   "start": 989.82,
   "duration": 4.56
  },
  {
   "text": "will occupy the fields of Ephraim and",
   "start": 992.19,
   "duration": 5.49
  },
  {
   "text": "Samaria and Benjamin will possess Gilead",
   "start": 994.38,
   "duration": 6.24
  },
  {
   "text": "in other words the Judah remnant will go",
   "start": 997.68,
   "duration": 6.84
  },
  {
   "text": "out and possess the land this company of",
   "start": 1000.62,
   "duration": 6.09
  },
  {
   "text": "Israelite exiles who are in Canaan will",
   "start": 1004.52,
   "duration": 5.07
  },
  {
   "text": "possess the land as far as Arif s the",
   "start": 1006.71,
   "duration": 6.08
  },
  {
   "text": "exiles from Jerusalem who are in chef",
   "start": 1009.59,
   "duration": 7.08
  },
  {
   "text": "Seth sepharad will possess the towns of",
   "start": 1012.79,
   "duration": 6.88
  },
  {
   "text": "the Negev deliverers will go up on Mount",
   "start": 1016.67,
   "duration": 5.58
  },
  {
   "text": "Zion to govern the mountains of Esau and",
   "start": 1019.67,
   "duration": 6.48
  },
  {
   "text": "the kingdom will be the Lord's now",
   "start": 1022.25,
   "duration": 6.089
  },
  {
   "text": "obviously if you read this from certain",
   "start": 1026.15,
   "duration": 4.65
  },
  {
   "text": "perspectives you see certain things the",
   "start": 1028.339,
   "duration": 4.411
  },
  {
   "text": "contemporary state of Israel will read",
   "start": 1030.8,
   "duration": 4.409
  },
  {
   "text": "this in a certain way and so be as read",
   "start": 1032.75,
   "duration": 4.5
  },
  {
   "text": "in a certain way that as I'm processing",
   "start": 1035.209,
   "duration": 3.961
  },
  {
   "text": "the sam harris video you would have",
   "start": 1037.25,
   "duration": 3.839
  },
  {
   "text": "particular objections to this is exactly",
   "start": 1039.17,
   "duration": 4.68
  },
  {
   "text": "the kind of thing he is objecting to",
   "start": 1041.089,
   "duration": 4.861
  },
  {
   "text": "but now pay attention as I mentioned the",
   "start": 1043.85,
   "duration": 5.46
  },
  {
   "text": "book of Nahum when prophecies went out",
   "start": 1045.95,
   "duration": 5.58
  },
  {
   "text": "they were recorded and they were kept",
   "start": 1049.31,
   "duration": 6.21
  },
  {
   "text": "and they were tracked and probably some",
   "start": 1051.53,
   "duration": 5.76
  },
  {
   "text": "of the prophecies we find in the Bible",
   "start": 1055.52,
   "duration": 4.26
  },
  {
   "text": "are the ones that people said when he",
   "start": 1057.29,
   "duration": 6.15
  },
  {
   "text": "when eaten fell they said AHA Obadiah",
   "start": 1059.78,
   "duration": 6.09
  },
  {
   "text": "the Lord must have been speaking through",
   "start": 1063.44,
   "duration": 4.979
  },
  {
   "text": "him and they're probably multiple",
   "start": 1065.87,
   "duration": 4.049
  },
  {
   "text": "their profits and in fact you can find",
   "start": 1068.419,
   "duration": 3.661
  },
  {
   "text": "it in the narrative books lots of",
   "start": 1069.919,
   "duration": 4.59
  },
  {
   "text": "profits around saying lots of things but",
   "start": 1072.08,
   "duration": 5.429
  },
  {
   "text": "these are the ones that rang true and so",
   "start": 1074.509,
   "duration": 6.36
  },
  {
   "text": "that's why these get encoded recorded in",
   "start": 1077.509,
   "duration": 5.67
  },
  {
   "text": "the book and these get seen as canonical",
   "start": 1080.869,
   "duration": 5.091
  },
  {
   "text": "as being a righteous word of the Lord",
   "start": 1083.179,
   "duration": 5.25
  },
  {
   "text": "but what does the Lord what does the",
   "start": 1085.96,
   "duration": 7.059
  },
  {
   "text": "word say was the word fully exhausted by",
   "start": 1088.429,
   "duration": 9.6
  },
  {
   "text": "the destruction of Edom well a lot of",
   "start": 1093.019,
   "duration": 6.24
  },
  {
   "text": "this has to do with this question of",
   "start": 1098.029,
   "duration": 2.58
  },
  {
   "text": "identity because this question of",
   "start": 1099.259,
   "duration": 3.6
  },
  {
   "text": "identity goes through a major shift in",
   "start": 1100.609,
   "duration": 5.4
  },
  {
   "text": "the transition from from the transition",
   "start": 1102.859,
   "duration": 5.91
  },
  {
   "text": "that Jesus inaugurates what gives you",
   "start": 1106.009,
   "duration": 5.941
  },
  {
   "text": "identity over what does that identity",
   "start": 1108.769,
   "duration": 8.16
  },
  {
   "text": "govern who says who's in and who's out",
   "start": 1111.95,
   "duration": 10.38
  },
  {
   "text": "is it bloodline or is it behavior and",
   "start": 1116.929,
   "duration": 7.44
  },
  {
   "text": "you can see in the Old Testament there's",
   "start": 1122.33,
   "duration": 5.429
  },
  {
   "text": "roots of this that that those who are",
   "start": 1124.369,
   "duration": 6.93
  },
  {
   "text": "not from the bloodline of Jacob could be",
   "start": 1127.759,
   "duration": 7.35
  },
  {
   "text": "grafted into Israel so what does it mean",
   "start": 1131.299,
   "duration": 6.301
  },
  {
   "text": "to be Chinese does does being Chinese",
   "start": 1135.109,
   "duration": 4.621
  },
  {
   "text": "mean to have a traditional Chinese",
   "start": 1137.6,
   "duration": 4.259
  },
  {
   "text": "wedding where the where the colors are",
   "start": 1139.73,
   "duration": 5.909
  },
  {
   "text": "predominantly red today wikipedia says",
   "start": 1141.859,
   "duration": 6.63
  },
  {
   "text": "these kinds of weddings in China are",
   "start": 1145.639,
   "duration": 5.76
  },
  {
   "text": "popular with the white dress and the",
   "start": 1148.489,
   "duration": 5.31
  },
  {
   "text": "white tux and any American will looking",
   "start": 1151.399,
   "duration": 4.831
  },
  {
   "text": "at this would say well this sure looks",
   "start": 1153.799,
   "duration": 4.59
  },
  {
   "text": "to me like a Western wedding",
   "start": 1156.23,
   "duration": 5.97
  },
  {
   "text": "so what is it to be Chinese what is it",
   "start": 1158.389,
   "duration": 7.1
  },
  {
   "text": "to be Western in our own contemporary",
   "start": 1162.2,
   "duration": 5.819
  },
  {
   "text": "culture here in America especially this",
   "start": 1165.489,
   "duration": 5.231
  },
  {
   "text": "melting pot we say well to be a true",
   "start": 1168.019,
   "duration": 6.66
  },
  {
   "text": "American is a national thing but what",
   "start": 1170.72,
   "duration": 7.559
  },
  {
   "text": "does it mean to be a Christian John the",
   "start": 1174.679,
   "duration": 8.161
  },
  {
   "text": "Baptist comes and he says this but when",
   "start": 1178.279,
   "duration": 6.12
  },
  {
   "text": "he saw many Pharisees and Sadducees",
   "start": 1182.84,
   "duration": 4.11
  },
  {
   "text": "coming to where he was baptizing he said",
   "start": 1184.399,
   "duration": 5.25
  },
  {
   "text": "to them you brood of vipers who warned",
   "start": 1186.95,
   "duration": 4.429
  },
  {
   "text": "you to flee from the coming wrath",
   "start": 1189.649,
   "duration": 4.16
  },
  {
   "text": "produce fruit in keeping with repentance",
   "start": 1191.379,
   "duration": 5.77
  },
  {
   "text": "and do not think to say to yourselves we",
   "start": 1193.809,
   "duration": 6.1
  },
  {
   "text": "have Abraham as our Father I tell you",
   "start": 1197.149,
   "duration": 4.4
  },
  {
   "text": "that out of these stones",
   "start": 1199.909,
   "duration": 3.98
  },
  {
   "text": "God can raise up children from Abraham",
   "start": 1201.549,
   "duration": 5.37
  },
  {
   "text": "the axe is already at the root of the",
   "start": 1203.889,
   "duration": 4.86
  },
  {
   "text": "tree and every tree that does not",
   "start": 1206.919,
   "duration": 4.531
  },
  {
   "text": "produce good fruit will be cut down and",
   "start": 1208.749,
   "duration": 6.211
  },
  {
   "text": "thrown into the fire in other words what",
   "start": 1211.45,
   "duration": 6.27
  },
  {
   "text": "John the Baptist is saying is the true",
   "start": 1214.96,
   "duration": 5.459
  },
  {
   "text": "sons of Israel are known by their",
   "start": 1217.72,
   "duration": 8.85
  },
  {
   "text": "behavior not simply by their blood John",
   "start": 1220.419,
   "duration": 7.921
  },
  {
   "text": "says i baptize you with water for",
   "start": 1226.57,
   "duration": 4.739
  },
  {
   "text": "repentance but after me comes one who",
   "start": 1228.34,
   "duration": 5.429
  },
  {
   "text": "was more powerful than I whose sandals I",
   "start": 1231.309,
   "duration": 4.98
  },
  {
   "text": "am not worthy to carry he will baptize",
   "start": 1233.769,
   "duration": 5.84
  },
  {
   "text": "you with the Holy Spirit and with fire",
   "start": 1236.289,
   "duration": 6.72
  },
  {
   "text": "his winnowing Fork is in his hand and he",
   "start": 1239.609,
   "duration": 5.65
  },
  {
   "text": "will clear his threshing floor gathering",
   "start": 1243.009,
   "duration": 4.8
  },
  {
   "text": "his wheat into the barn and burning up",
   "start": 1245.259,
   "duration": 6.3
  },
  {
   "text": "the chaff with unquenchable fire and we",
   "start": 1247.809,
   "duration": 5.641
  },
  {
   "text": "see in a sense all the elements here",
   "start": 1251.559,
   "duration": 6.021
  },
  {
   "text": "gathered breath and earth water and fire",
   "start": 1253.45,
   "duration": 8.969
  },
  {
   "text": "who does this who is this now we think",
   "start": 1257.58,
   "duration": 8.439
  },
  {
   "text": "well this is Jesus of course this is",
   "start": 1262.419,
   "duration": 6.36
  },
  {
   "text": "Jesus who he's talking to you he's",
   "start": 1266.019,
   "duration": 5.431
  },
  {
   "text": "talking about John the Baptist is an",
   "start": 1268.779,
   "duration": 5.64
  },
  {
   "text": "interesting individual he sees an aspect",
   "start": 1271.45,
   "duration": 5.28
  },
  {
   "text": "of Jesus ministry in fact like all the",
   "start": 1274.419,
   "duration": 6.271
  },
  {
   "text": "other prophets he sees long he he sees",
   "start": 1276.73,
   "duration": 7.139
  },
  {
   "text": "far away the day of the Lord that is",
   "start": 1280.69,
   "duration": 4.739
  },
  {
   "text": "coming and so when you listen to John",
   "start": 1283.869,
   "duration": 4.38
  },
  {
   "text": "you hear him reflect the the prophets of",
   "start": 1285.429,
   "duration": 4.2
  },
  {
   "text": "the Old Testament he is preaching the",
   "start": 1288.249,
   "duration": 3.831
  },
  {
   "text": "day of the Lord and he is warning them",
   "start": 1289.629,
   "duration": 5.01
  },
  {
   "text": "but when he had more trouble seeing is",
   "start": 1292.08,
   "duration": 4.689
  },
  {
   "text": "the ministry than the mission that Jesus",
   "start": 1294.639,
   "duration": 5.1
  },
  {
   "text": "had closed up because Jesus in that",
   "start": 1296.769,
   "duration": 5.671
  },
  {
   "text": "moment was coming to bear judgment not",
   "start": 1299.739,
   "duration": 5.94
  },
  {
   "text": "to bring it he was coming to bear the",
   "start": 1302.44,
   "duration": 6.809
  },
  {
   "text": "sins of the guilty not to unleash",
   "start": 1305.679,
   "duration": 6.84
  },
  {
   "text": "judgment upon the guilty he was coming",
   "start": 1309.249,
   "duration": 7.341
  },
  {
   "text": "to be that kind of Messiah",
   "start": 1312.519,
   "duration": 4.071
  },
  {
   "text": "American culture gets this by demoting",
   "start": 1320.669,
   "duration": 5.26
  },
  {
   "text": "the bloodlines from Christianity your",
   "start": 1323.59,
   "duration": 4.949
  },
  {
   "text": "ethnicity is no barrier for entry to",
   "start": 1325.929,
   "duration": 5.82
  },
  {
   "text": "becoming a true child of Abraham and and",
   "start": 1328.539,
   "duration": 5.401
  },
  {
   "text": "this then gets into American culture and",
   "start": 1331.749,
   "duration": 5.16
  },
  {
   "text": "you can find this expressed even in this",
   "start": 1333.94,
   "duration": 7.41
  },
  {
   "text": "even in the even in the movie crazy rich",
   "start": 1336.909,
   "duration": 6.15
  },
  {
   "text": "Asians now it's very interesting at the",
   "start": 1341.35,
   "duration": 3.72
  },
  {
   "text": "beginning of the movie where the mother",
   "start": 1343.059,
   "duration": 5.041
  },
  {
   "text": "who is so opposed to the daughter at",
   "start": 1345.07,
   "duration": 5.939
  },
  {
   "text": "least initially is having a Bible study",
   "start": 1348.1,
   "duration": 6.299
  },
  {
   "text": "with her friends and if I were doing a",
   "start": 1351.009,
   "duration": 6.211
  },
  {
   "text": "movie review I'd probably pick up on",
   "start": 1354.399,
   "duration": 4.591
  },
  {
   "text": "that a little bit but the mother is also",
   "start": 1357.22,
   "duration": 4.439
  },
  {
   "text": "I don't want to give it any spoilers so",
   "start": 1358.99,
   "duration": 4.95
  },
  {
   "text": "you can I don't want to spoil the movie",
   "start": 1361.659,
   "duration": 4.291
  },
  {
   "text": "for you if you watch it but but you'll",
   "start": 1363.94,
   "duration": 3.839
  },
  {
   "text": "notice in this conversation that is",
   "start": 1365.95,
   "duration": 3.99
  },
  {
   "text": "going under the surface this is this is",
   "start": 1367.779,
   "duration": 4.681
  },
  {
   "text": "what gets into Rachel Chu and and even",
   "start": 1369.94,
   "duration": 4.109
  },
  {
   "text": "though there's no evidence that she's a",
   "start": 1372.46,
   "duration": 3.78
  },
  {
   "text": "Christian in the movie this gets carried",
   "start": 1374.049,
   "duration": 4.801
  },
  {
   "text": "on in the culture right through to her",
   "start": 1376.24,
   "duration": 5.279
  },
  {
   "text": "and and so what Christian a Christianity",
   "start": 1378.85,
   "duration": 4.949
  },
  {
   "text": "does is is promotes the message that is",
   "start": 1381.519,
   "duration": 4.951
  },
  {
   "text": "found in Genesis 1 that all human beings",
   "start": 1383.799,
   "duration": 5.311
  },
  {
   "text": "are image bearers and this is this is in",
   "start": 1386.47,
   "duration": 4.74
  },
  {
   "text": "seed in the Old Testament it comes out",
   "start": 1389.11,
   "duration": 5.039
  },
  {
   "text": "to full flourishing in the Apostle Paul",
   "start": 1391.21,
   "duration": 6.659
  },
  {
   "text": "and and and this is this is where we get",
   "start": 1394.149,
   "duration": 6.301
  },
  {
   "text": "that there's this is where we see that",
   "start": 1397.869,
   "duration": 5.16
  },
  {
   "text": "Jesus is not just the Messiah for a",
   "start": 1400.45,
   "duration": 5.25
  },
  {
   "text": "particular nation but he's the savior of",
   "start": 1403.029,
   "duration": 6.331
  },
  {
   "text": "all humanity but at the same time in",
   "start": 1405.7,
   "duration": 5.4
  },
  {
   "text": "this world the grass withers and the",
   "start": 1409.36,
   "duration": 3.99
  },
  {
   "text": "flower fades and its place remembers",
   "start": 1411.1,
   "duration": 5.429
  },
  {
   "text": "that no more and God raises up children",
   "start": 1413.35,
   "duration": 6.329
  },
  {
   "text": "of Abraham from the stones and then the",
   "start": 1416.529,
   "duration": 5.911
  },
  {
   "text": "question for you is do you believe he",
   "start": 1419.679,
   "duration": 6.6
  },
  {
   "text": "can raise you and can you act like he",
   "start": 1422.44,
   "duration": 6.02
  },
  {
   "text": "will",
   "start": 1426.279,
   "duration": 2.181
  }
 ]
}