{"video_id": "Fyg0YQJkmAo", "channel_id": "UCtCTSf3UwRU14nYWr_xm-dQ", "channel_name": "Jonathan Pageau", "title": "Rise of Jordan Peterson - Live Q&A with Jonathan Pageau", "url": "https://www.youtube.com/watch?v=Fyg0YQJkmAo", "date": "2019-10-08", "description": "I hosted the showing of Patricia Marrcoccia's Rise of Jordan Peterson in Montreal. This is the short introduction and then an extensive Q&A answering very diverse questions from the audience.\n\nMy links:\n\nSupport this channel: https://thesymbolicworld.com/support/\n\npatreon: http://www.patreon.com/pageauvideos\nsubscribestar: https://www.subscribestar.com/jonathan-pageau\npaypal: http://www.paypal.me/JonathanPageau\n\nwebsite: http://www.thesymbolicworld.com\nfacebook: http://www.facebook.com/TheSymbolicWorld\ntwitter: http://www.twitter.com/pageaujonathan\nBitchute:  https://www.bitchute.com/channel/pageaujonathan/\nDtube: https://steemit.com/@symbolism\n\nThe unofficial facebook discussion group: \nhttps://www.facebook.com/groups/1989208418065298/\n\nThe outro to my videos was written by Matthew Wilkinson\n\nMy website designers,  Anomalist Design: https://www.anomalistdesign.com/\n\nThe music at the opening is Russian Eastern Overture, by Rimsky Korsakov.", "duration": 3017, "transcript_parts": [{"text": "hello everybody first question", "start": 4.19, "duration": 4.41}, {"text": "so Patricia Marco chia and mozzie are", "start": 21.619, "duration": 8.861}, {"text": "hoaxes the event in Montreal which I", "start": 27.35, "duration": 4.689}, {"text": "graciously accepted - my name is", "start": 30.48, "duration": 4.259}, {"text": "Jonathan pego you see that I you will", "start": 32.039, "duration": 5.07}, {"text": "see my face in this movie I I haven't", "start": 34.739, "duration": 6.721}, {"text": "seen it so I don't know don't don't", "start": 37.109, "duration": 7.441}, {"text": "start hunting me off the tour I no idea", "start": 41.46, "duration": 4.859}, {"text": "but I've been hearing really good things", "start": 44.55, "duration": 3.87}, {"text": "about the documentary so I'm excited to", "start": 46.319, "duration": 5.941}, {"text": "see it with you guys i if you don't know", "start": 48.42, "duration": 5.399}, {"text": "a little bit the story of the movie", "start": 52.26, "duration": 5.969}, {"text": "Patricia was filming a documentary about", "start": 53.819, "duration": 6.691}, {"text": "her Peterson and his relationship with", "start": 58.229, "duration": 3.84}, {"text": "his friend Charles who was Native", "start": 60.51, "duration": 4.35}, {"text": "American and who's a carver and Jordan", "start": 62.069, "duration": 4.381}, {"text": "and this man had developed a very close", "start": 64.86, "duration": 3.45}, {"text": "relationship to the extent that Jordan", "start": 66.45, "duration": 4.98}, {"text": "was adopted into his family so Patricia", "start": 68.31, "duration": 6.6}, {"text": "was filming this story as the events", "start": 71.43, "duration": 6.57}, {"text": "around her Houston erupted and that's", "start": 74.91, "duration": 6.06}, {"text": "why she got this inside scoop on the", "start": 78.0, "duration": 5.55}, {"text": "event and Patricia and I GRE of this", "start": 80.97, "duration": 6.39}, {"text": "very normal liberal left-leaning people", "start": 83.55, "duration": 5.91}, {"text": "and c'mon oh all of a sudden for", "start": 87.36, "duration": 4.77}, {"text": "let's see this crazy whirlwind around", "start": 89.46, "duration": 6.0}, {"text": "him and are trying to make sense of why", "start": 92.13, "duration": 6.6}, {"text": "such extreme positions are being taken", "start": 95.46, "duration": 4.71}, {"text": "regarding him", "start": 98.73, "duration": 4.41}, {"text": "and so the documentary was kind of", "start": 100.17, "duration": 6.09}, {"text": "slowly built up as he was in this world", "start": 103.14, "duration": 5.16}, {"text": "when filming things you know filming the", "start": 106.26, "duration": 4.2}, {"text": "events and putting it together she's", "start": 108.3, "duration": 5.25}, {"text": "still actually trying to put together", "start": 110.46, "duration": 5.43}, {"text": "the the documentary based on Jordans", "start": 113.55, "duration": 3.81}, {"text": "relationship with trouble which should", "start": 115.89, "duration": 3.15}, {"text": "come up hopefully I think their", "start": 117.36, "duration": 3.15}, {"text": "crowdfunding right now for that", "start": 119.04, "duration": 4.62}, {"text": "and so I'm ignoring a few years ago", "start": 120.51, "duration": 5.609}, {"text": "again also before this world when I", "start": 123.66, "duration": 4.829}, {"text": "heard him on CBC you know and I was", "start": 126.119, "duration": 3.84}, {"text": "really excited about some of his ideas", "start": 128.489, "duration": 3.301}, {"text": "about psychology how the understood", "start": 129.959, "duration": 3.871}, {"text": "religion how he understood some of the", "start": 131.79, "duration": 4.5}, {"text": "problems were facing and myself as well", "start": 133.83, "duration": 4.8}, {"text": "was caught up in this crazy story all", "start": 136.29, "duration": 3.75}, {"text": "the sudden all these extreme position", "start": 138.63, "duration": 5.49}, {"text": "being pulled on each side of him and and", "start": 140.04, "duration": 6.15}, {"text": "so I just been following the story just", "start": 144.12, "duration": 4.589}, {"text": "as you guys and I'm excited to see how", "start": 146.19, "duration": 5.58}, {"text": "Patricia and mozzie are going to tell", "start": 148.709, "duration": 5.34}, {"text": "the story so after the event I'm going", "start": 151.77, "duration": 4.73}, {"text": "to give a short question and answer", "start": 154.049, "duration": 4.591}, {"text": "obviously I can't answer everything", "start": 156.5, "duration": 3.88}, {"text": "about computers and I'm not going", "start": 158.64, "duration": 3.48}, {"text": "Peterson there's a lot of things about", "start": 160.38, "duration": 2.79}, {"text": "the man that I love", "start": 162.12, "duration": 3.15}, {"text": "much I also have my criticisms of him as", "start": 163.17, "duration": 4.71}, {"text": "I'm sure all of you do and the great", "start": 165.27, "duration": 4.77}, {"text": "thing about dort is actually is willing", "start": 167.88, "duration": 4.02}, {"text": "to make those criticisms so if you have", "start": 170.04, "duration": 4.59}, {"text": "questions for me at the end I will stick", "start": 171.9, "duration": 4.32}, {"text": "around and be willing to answer some", "start": 174.63, "duration": 12.45}, {"text": "questions so enjoy the movie so if you", "start": 176.22, "duration": 12.45}, {"text": "guys have if you if there's something", "start": 187.08, "duration": 3.18}, {"text": "you want to ask me obviously like I said", "start": 188.67, "duration": 3.81}, {"text": "I can't enter I can't I'm not Jordan", "start": 190.26, "duration": 4.259}, {"text": "Peterson I can't answer for him but I", "start": 192.48, "duration": 4.47}, {"text": "can try to answer as best as I can the", "start": 194.519, "duration": 4.411}, {"text": "questions you have see what was it you", "start": 196.95, "duration": 3.33}, {"text": "kissed you on message if any of one of", "start": 198.93, "duration": 3.45}, {"text": "us said if you ask a question in English", "start": 200.28, "duration": 4.709}, {"text": "and I'll answer in English so anybody", "start": 202.38, "duration": 18.359}, {"text": "has something they want to ask um I", "start": 204.989, "duration": 18.301}, {"text": "don't know how how they receive it right", "start": 220.739, "duration": 4.47}, {"text": "now but one thing is for sure is that", "start": 223.29, "duration": 6.479}, {"text": "this movie was made out of a CBC special", "start": 225.209, "duration": 6.691}, {"text": "and I'm so you saw the CBC spectrum and", "start": 229.769, "duration": 3.931}, {"text": "so for them it actually was an", "start": 231.9, "duration": 4.95}, {"text": "opportunity to to put in the content", "start": 233.7, "duration": 4.83}, {"text": "that they had wanted to put in because", "start": 236.85, "duration": 3.449}, {"text": "in the CBC special they obviously were", "start": 238.53, "duration": 4.079}, {"text": "somewhat you know they were under the", "start": 240.299, "duration": 3.871}, {"text": "CBC they had certain requirements that", "start": 242.609, "duration": 3.72}, {"text": "they had to fill and so making this", "start": 244.17, "duration": 3.42}, {"text": "movie was a way for them to do that", "start": 246.329, "duration": 3.571}, {"text": "which to put in more content that they", "start": 247.59, "duration": 4.38}, {"text": "wanted to put in so maybe there's if", "start": 249.9, "duration": 3.809}, {"text": "there's some content that they wanted to", "start": 251.97, "duration": 2.55}, {"text": "put in that it", "start": 253.709, "duration": 5.881}, {"text": "I don't know well see these I don't know", "start": 254.52, "duration": 6.9}, {"text": "CBC they had a certain angle that they", "start": 259.59, "duration": 3.87}, {"text": "wanted they did it in the way that you", "start": 261.42, "duration": 3.75}, {"text": "know I don't know I don't know I don't", "start": 263.46, "duration": 3.9}, {"text": "want to answer that but it was also very", "start": 265.17, "duration": 3.99}, {"text": "short and they felt like they couldn't", "start": 267.36, "duration": 3.54}, {"text": "get everything they wanted to get out", "start": 269.16, "duration": 4.95}, {"text": "into that into that video so so this was", "start": 270.9, "duration": 4.65}, {"text": "kind of the way that they could expand", "start": 274.11, "duration": 6.45}, {"text": "the discussion and make it bigger what", "start": 275.55, "duration": 10.97}, {"text": "the movie I think it's fair I think that", "start": 280.56, "duration": 5.96}, {"text": "how can I say this I would say that it's", "start": 287.42, "duration": 5.74}, {"text": "hard it's hard because Jordan is such a", "start": 291.0, "duration": 4.47}, {"text": "polarizing figure and he's my friend so", "start": 293.16, "duration": 5.4}, {"text": "I I think it's fair in the sense that I", "start": 295.47, "duration": 5.67}, {"text": "feel like they presented the people that", "start": 298.56, "duration": 4.5}, {"text": "were closest to him that criticized him", "start": 301.14, "duration": 3.6}, {"text": "I felt like the criticism that they", "start": 303.06, "duration": 3.42}, {"text": "posed they they put up some of the more", "start": 304.74, "duration": 3.54}, {"text": "controversial things that you've said so", "start": 306.48, "duration": 3.15}, {"text": "I feel like they were able to show a", "start": 308.28, "duration": 3.0}, {"text": "little bit of the controversy around him", "start": 309.63, "duration": 2.64}, {"text": "some of the things you said that were", "start": 311.28, "duration": 3.84}, {"text": "kind of edgy kind of on the edge but at", "start": 312.27, "duration": 5.94}, {"text": "the same time I I feel like what comes", "start": 315.12, "duration": 4.62}, {"text": "out is very positive but that's also", "start": 318.21, "duration": 4.17}, {"text": "because of my own what I bring to it as", "start": 319.74, "duration": 4.85}, {"text": "well", "start": 322.38, "duration": 2.21}, {"text": "just focusing so much on Jordans", "start": 328.569, "duration": 7.33}, {"text": "polarizing effect that his ideas like", "start": 332.199, "duration": 5.14}, {"text": "his deep ideas fallen to the wayside", "start": 335.899, "duration": 6.21}, {"text": "like having seen his biblical things and", "start": 337.339, "duration": 6.9}, {"text": "his thoughts on alchemy and maps of", "start": 342.109, "duration": 4.41}, {"text": "meaning like all his deep spots you find", "start": 344.239, "duration": 4.8}, {"text": "he's frustrated that he spent so much", "start": 346.519, "duration": 4.05}, {"text": "time talking about that stuff but he", "start": 349.039, "duration": 4.62}, {"text": "loses out on investigating those ideas", "start": 350.569, "duration": 7.13}, {"text": "further with people um I think they", "start": 353.659, "duration": 8.701}, {"text": "pause okay all right so he asked if the", "start": 357.699, "duration": 7.21}, {"text": "polarization around Jordan if it maybe", "start": 362.36, "duration": 4.289}, {"text": "is taking away from what is really deep", "start": 364.909, "duration": 3.69}, {"text": "messages in terms of his understanding", "start": 366.649, "duration": 4.26}, {"text": "of religion is insights into alchemy", "start": 368.599, "duration": 4.71}, {"text": "into different aspects of reality", "start": 370.909, "duration": 4.98}, {"text": "if this polarizing effect is taking away", "start": 373.309, "duration": 5.01}, {"text": "from that I think that I think that it's", "start": 375.889, "duration": 4.23}, {"text": "a deep how can I say this it's like a", "start": 378.319, "duration": 4.56}, {"text": "50/50 thing we're on the one hand I", "start": 380.119, "duration": 5.01}, {"text": "think Jordan is a very smart person and", "start": 382.879, "duration": 6.39}, {"text": "extremely can I say this he's very", "start": 385.129, "duration": 6.54}, {"text": "tactical and so he was able also to use", "start": 389.269, "duration": 3.93}, {"text": "this controversy that he didn't expect", "start": 391.669, "duration": 4.441}, {"text": "to be able to talk about the things that", "start": 393.199, "duration": 20.1}, {"text": "he really so he said he said that Jordan", "start": 396.11, "duration": 18.539}, {"text": "has some insights on prophetic dreams", "start": 413.299, "duration": 4.2}, {"text": "and in the video it's shown to make it", "start": 414.649, "duration": 4.8}, {"text": "look a bit crazy but that is something", "start": 417.499, "duration": 5.12}, {"text": "that Jung has talked about well I think", "start": 419.449, "duration": 5.88}, {"text": "in that section and we're really trying", "start": 422.619, "duration": 5.05}, {"text": "to show the point of view of the person", "start": 425.329, "duration": 4.89}, {"text": "his friend who criticized him so I think", "start": 427.669, "duration": 4.341}, {"text": "that's probably why it came out that", "start": 430.219, "duration": 7.811}, {"text": "but uh I just said just a follow-up", "start": 432.01, "duration": 11.33}, {"text": "ready big part of the Greek philosopher", "start": 438.03, "duration": 5.31}, {"text": "yeah so you asked if I know how dort is", "start": 452.94, "duration": 5.4}, {"text": "doing because he's a he's worried um", "start": 455.5, "duration": 7.23}, {"text": "yeah and his wife I it was very strange", "start": 458.34, "duration": 6.85}, {"text": "because I was having very short you know", "start": 462.73, "duration": 3.99}, {"text": "I had this kind of short little email", "start": 465.19, "duration": 3.57}, {"text": "exchanges with him you know we write", "start": 466.72, "duration": 3.69}, {"text": "notes back and forth after a few months", "start": 468.76, "duration": 4.56}, {"text": "and I've been really following Tami's", "start": 470.41, "duration": 6.75}, {"text": "story and and so when things started to", "start": 473.32, "duration": 6.36}, {"text": "get better I got a note from him and he", "start": 477.16, "duration": 3.87}, {"text": "was saying that it seemed like it was", "start": 479.68, "duration": 2.94}, {"text": "getting better and it was kind of this", "start": 481.03, "duration": 4.11}, {"text": "strange surprising event you know they", "start": 482.62, "duration": 4.26}, {"text": "don't really know exactly how it is that", "start": 485.14, "duration": 3.45}, {"text": "it happened but she's getting better and", "start": 486.88, "duration": 4.05}, {"text": "then I learned about his own problems", "start": 488.59, "duration": 5.31}, {"text": "through Mikayla's video like most of us", "start": 490.93, "duration": 6.78}, {"text": "did and so since then I I kind of waited", "start": 493.9, "duration": 5.7}, {"text": "a little bit I send it was a small short", "start": 497.71, "duration": 4.14}, {"text": "message he didn't answer but I don't", "start": 499.6, "duration": 4.2}, {"text": "know I don't know what he's I think that", "start": 501.85, "duration": 6.03}, {"text": "Jordan is a very he's very smart and he", "start": 503.8, "duration": 5.91}, {"text": "realized his what was going on in terms", "start": 507.88, "duration": 3.36}, {"text": "of the medication that he was taking and", "start": 509.71, "duration": 3.209}, {"text": "he probably just said okay I need to nip", "start": 511.24, "duration": 3.39}, {"text": "this in the bud because he wants to get", "start": 512.919, "duration": 4.201}, {"text": "back he's writing another book he has so", "start": 514.63, "duration": 3.96}, {"text": "many things that he wants to do so he", "start": 517.12, "duration": 3.51}, {"text": "just wants to get rid of this problem", "start": 518.59, "duration": 3.75}, {"text": "and then move on that's the way I", "start": 520.63, "duration": 3.78}, {"text": "perceive it but I don't know Ivan I", "start": 522.34, "duration": 5.33}, {"text": "haven't had any firm in sense", "start": 524.41, "duration": 3.26}, {"text": "okay so he's saying that he heard an", "start": 532.389, "duration": 4.69}, {"text": "update today that it was a big reaction", "start": 535.069, "duration": 7.08}, {"text": "- yeah I'll have this fringe medication", "start": 537.079, "duration": 7.26}, {"text": "for anxiety that he was reacting - yeah", "start": 542.149, "duration": 4.141}, {"text": "that's that's what I heard as well and", "start": 544.339, "duration": 3.24}, {"text": "then she's checked if he checked himself", "start": 546.29, "duration": 3.299}, {"text": "into a rehab center to be able to kind", "start": 547.579, "duration": 4.471}, {"text": "of just get it out of his system and and", "start": 549.589, "duration": 5.55}, {"text": "and move on am I correct in my", "start": 552.05, "duration": 4.289}, {"text": "understanding if this is the only", "start": 555.139, "duration": 4.831}, {"text": "showing of this documentary so he asked", "start": 556.339, "duration": 5.011}, {"text": "if it's the only showing of the", "start": 559.97, "duration": 2.969}, {"text": "documentary Canada no it's going to be", "start": 561.35, "duration": 4.349}, {"text": "shown in several places in Canada it's", "start": 562.939, "duration": 4.44}, {"text": "going to be I think the only showing in", "start": 565.699, "duration": 4.83}, {"text": "Montreal but you know it got shut down", "start": 567.379, "duration": 7.2}, {"text": "in Toronto because someone who works for", "start": 570.529, "duration": 8.37}, {"text": "the movie theater complained about how", "start": 574.579, "duration": 6.36}, {"text": "country how some things were were", "start": 578.899, "duration": 4.321}, {"text": "offensive and now it just got shut down", "start": 580.939, "duration": 4.801}, {"text": "in New York or they did one showing in", "start": 583.22, "duration": 5.28}, {"text": "New York and it was sold out and then", "start": 585.74, "duration": 3.81}, {"text": "they said okay so we're gonna add", "start": 588.5, "duration": 2.85}, {"text": "another showing and it was shut down", "start": 589.55, "duration": 2.31}, {"text": "that", "start": 591.35, "duration": 2.58}, {"text": "Maziar send me a message just this", "start": 591.86, "duration": 4.26}, {"text": "morning to tell me so it's crazy because", "start": 593.93, "duration": 4.349}, {"text": "when you watch a documentary it's hard", "start": 596.12, "duration": 4.17}, {"text": "to imagine that someone could have", "start": 598.279, "duration": 5.031}, {"text": "presented a fair representation", "start": 600.29, "duration": 5.489}, {"text": "considering that it is about drug person", "start": 603.31, "duration": 4.54}, {"text": "than it is a video it is it is the", "start": 605.779, "duration": 4.11}, {"text": "documentary about him but that there is", "start": 607.85, "duration": 4.5}, {"text": "this desire to fairly show all the sides", "start": 609.889, "duration": 4.861}, {"text": "that despite that there's still this", "start": 612.35, "duration": 9.12}, {"text": "desire to still shut him down so so so", "start": 614.75, "duration": 7.889}, {"text": "she asked what was offensive I don't", "start": 621.47, "duration": 3.78}, {"text": "know I don't know what was offensive I", "start": 622.639, "duration": 3.121}, {"text": "mean", "start": 625.25, "duration": 2.91}, {"text": "I think it had to do with the same issue", "start": 625.76, "duration": 4.29}, {"text": "that from the beginning that to do it", "start": 628.16, "duration": 7.07}, {"text": "with with with the transgender questions", "start": 630.05, "duration": 5.18}, {"text": "so says expression is something that", "start": 643.99, "duration": 5.17}, {"text": "affects us here in Canada but is not", "start": 647.3, "duration": 3.87}, {"text": "necessarily something that is affected", "start": 649.16, "duration": 3.39}, {"text": "people in south of the border I think", "start": 651.17, "duration": 3.51}, {"text": "it's a question that is being posed", "start": 652.55, "duration": 3.0}, {"text": "right now", "start": 654.68, "duration": 2.969}, {"text": "you know if there's so many confluence", "start": 655.55, "duration": 3.599}, {"text": "of events that are bringing this whole", "start": 657.649, "duration": 3.721}, {"text": "freedom of expression question social", "start": 659.149, "duration": 4.651}, {"text": "media the internet all these things have", "start": 661.37, "duration": 6.23}, {"text": "opened up the door for all kinds of", "start": 663.8, "duration": 5.94}, {"text": "possibilities of expression that we", "start": 667.6, "duration": 3.88}, {"text": "didn't realize that were before", "start": 669.74, "duration": 3.27}, {"text": "anonymous you know like all these", "start": 671.48, "duration": 3.78}, {"text": "anonymous people online that say the", "start": 673.01, "duration": 3.72}, {"text": "wildest things because they're anonymous", "start": 675.26, "duration": 3.6}, {"text": "all these things they didn't exist for", "start": 676.73, "duration": 4.02}, {"text": "them so this is all new and no people", "start": 678.86, "duration": 4.02}, {"text": "are trying to figure out how do we deal", "start": 680.75, "duration": 4.11}, {"text": "with this how far do we let it go you", "start": 682.88, "duration": 3.87}, {"text": "know and so it's a it's a difficult it's", "start": 684.86, "duration": 3.9}, {"text": "a difficult problem but it's sure that", "start": 686.75, "duration": 4.23}, {"text": "in the u.s. people aren't protected by", "start": 688.76, "duration": 4.86}, {"text": "the Constitution itself and so they're", "start": 690.98, "duration": 4.83}, {"text": "you know those that are for freedom of", "start": 693.62, "duration": 3.87}, {"text": "speech they have something to stand upon", "start": 695.81, "duration": 3.54}, {"text": "where whereas in Canada we don't have", "start": 697.49, "duration": 4.409}, {"text": "that constitutional stand we just have a", "start": 699.35, "duration": 5.34}, {"text": "kind of common law or a common vision of", "start": 701.899, "duration": 6.93}, {"text": "what how we imagine freedom in a Western", "start": 704.69, "duration": 6.78}, {"text": "society but not necessarily it's not as", "start": 708.829, "duration": 6.331}, {"text": "ingrained in our culture for sure yes", "start": 711.47, "duration": 8.549}, {"text": "sir so he asked if the film will be", "start": 715.16, "duration": 6.0}, {"text": "available online yes they are", "start": 720.019, "duration": 3.0}, {"text": "negotiating right now is for sure it's", "start": 721.16, "duration": 5.85}, {"text": "going to be on Apple iTunes and they're", "start": 723.019, "duration": 5.19}, {"text": "negotiating with other streaming", "start": 727.01, "duration": 3.71}, {"text": "platforms", "start": 728.209, "duration": 2.511}, {"text": "he's asking for a movie poster I don't", "start": 732.48, "duration": 25.27}, {"text": "know so he asks because the movie didn't", "start": 735.01, "duration": 25.53}, {"text": "deal with your biblical series he's", "start": 757.75, "duration": 6.269}, {"text": "asking me if about that if I if we've", "start": 760.54, "duration": 4.859}, {"text": "talked about it if there's something", "start": 764.019, "duration": 3.271}, {"text": "what I think about the biblical series I", "start": 765.399, "duration": 4.771}, {"text": "think that doors biblical series during", "start": 767.29, "duration": 5.64}, {"text": "pinnacle series are on the one hand is", "start": 770.17, "duration": 4.01}, {"text": "amazing", "start": 772.93, "duration": 4.5}, {"text": "this amazing thing that came about where", "start": 774.18, "duration": 6.07}, {"text": "here's this professor talking about the", "start": 777.43, "duration": 3.45}, {"text": "Bible", "start": 780.25, "duration": 2.459}, {"text": "trying to get to the deepest meaning", "start": 780.88, "duration": 3.86}, {"text": "that you can find in the Bible and", "start": 782.709, "duration": 5.31}, {"text": "millions of people watching it and it's", "start": 784.74, "duration": 5.74}, {"text": "and it's just astounding that first", "start": 788.019, "duration": 4.411}, {"text": "video about what is God I mean I think", "start": 790.48, "duration": 3.81}, {"text": "it's it's got millions of views by now", "start": 792.43, "duration": 4.32}, {"text": "so I thought it was just astounding and", "start": 794.29, "duration": 5.31}, {"text": "then about the biblical lectures", "start": 796.75, "duration": 5.61}, {"text": "themselves sometimes he says great", "start": 799.6, "duration": 4.65}, {"text": "amazing things and sometimes he says", "start": 802.36, "duration": 3.69}, {"text": "things that are questionable sometimes", "start": 804.25, "duration": 3.45}, {"text": "he says things that are kind of just we", "start": 806.05, "duration": 2.97}, {"text": "don't know where he gets them from and", "start": 807.7, "duration": 3.449}, {"text": "and if like sounds like this wild roller", "start": 809.02, "duration": 3.9}, {"text": "coaster and yeah that's Jordan Peterson", "start": 811.149, "duration": 3.81}, {"text": "that's your medicine he is like I'm", "start": 812.92, "duration": 3.81}, {"text": "gonna take you on this trip that I'm on", "start": 814.959, "duration": 4.231}, {"text": "and I'm not sure where exactly where I'm", "start": 816.73, "duration": 4.229}, {"text": "going I'm gonna ride this and I'm going", "start": 819.19, "duration": 3.66}, {"text": "to to pay attention to what people are", "start": 820.959, "duration": 2.881}, {"text": "saying and I'm going", "start": 822.85, "duration": 3.57}, {"text": "I'm willing to change my opinion if I'm", "start": 823.84, "duration": 4.86}, {"text": "saying something too weird and so he so", "start": 826.42, "duration": 3.63}, {"text": "when you watch the video if you like", "start": 828.7, "duration": 3.12}, {"text": "sometimes sometimes like wow this", "start": 830.05, "duration": 3.45}, {"text": "amazing insight and then where is he", "start": 831.82, "duration": 2.01}, {"text": "going", "start": 833.5, "duration": 1.68}, {"text": "what's he said I don't understand why", "start": 833.83, "duration": 2.97}, {"text": "he's going there and no wow this amazing", "start": 835.18, "duration": 3.21}, {"text": "insight so that's how I feel about his", "start": 836.8, "duration": 3.479}, {"text": "biblical series I would love to have", "start": 838.39, "duration": 4.62}, {"text": "more time to talk to him about that but", "start": 840.279, "duration": 5.551}, {"text": "to be honest Jordan has become I mean if", "start": 843.01, "duration": 5.01}, {"text": "Tammy says that she's lost him to the", "start": 845.83, "duration": 3.72}, {"text": "world for sure I think all of his", "start": 848.02, "duration": 4.11}, {"text": "friends feel similar like I have little", "start": 849.55, "duration": 5.16}, {"text": "tidbits little emails from Jordan and", "start": 852.13, "duration": 4.53}, {"text": "and he regrets it he says you know I'm", "start": 854.71, "duration": 3.87}, {"text": "sorry I'm not able to be more present", "start": 856.66, "duration": 4.26}, {"text": "but that's that's reality yeah I haven't", "start": 858.58, "duration": 7.07}, {"text": "seen Jordan in I guess since 2000 late", "start": 860.92, "duration": 9.02}, {"text": "2008 early 2018", "start": 865.65, "duration": 4.29}, {"text": "so I just want to clarify that free", "start": 890.06, "duration": 3.719}, {"text": "speech is one thing in Canada the", "start": 892.01, "duration": 4.23}, {"text": "freedom of expression is an entirely", "start": 893.779, "duration": 4.411}, {"text": "other thing so I would encourage", "start": 896.24, "duration": 8.07}, {"text": "everybody to raise some freedoms thank", "start": 898.19, "duration": 8.399}, {"text": "you so he said that we do have a Charter", "start": 904.31, "duration": 4.17}, {"text": "of Rights and Freedoms and he encourages", "start": 906.589, "duration": 4.231}, {"text": "everybody here to see what the what arch", "start": 908.48, "duration": 4.5}, {"text": "Canadian Charter says about freedom of", "start": 910.82, "duration": 4.37}, {"text": "speech", "start": 912.98, "duration": 2.21}, {"text": "[Music]", "start": 943.91, "duration": 3.03}, {"text": "[Music]", "start": 963.32, "duration": 3.029}, {"text": "[Music]", "start": 970.91, "duration": 3.09}, {"text": "Madame an experienced commercial chicken", "start": 977.52, "duration": 7.02}, {"text": "meat director Madhan Verma modernity jjz", "start": 980.38, "duration": 7.7}, {"text": "transitory male-centric contact a", "start": 984.54, "duration": 8.16}, {"text": "whiskey tax Schedule D diversification", "start": 988.08, "duration": 8.8}, {"text": "atomic older geomatica lives and Dwight", "start": 992.7, "duration": 6.759}, {"text": "Yoakam a crochet edge or del bosque a", "start": 996.88, "duration": 6.209}, {"text": "javelin developer the personals at work", "start": 999.459, "duration": 9.541}, {"text": "Canada via Nepal is so common necessary", "start": 1003.089, "duration": 12.56}, {"text": "ruyan grtt Sabrina nationals here", "start": 1009.0, "duration": 10.7}, {"text": "Mexico City video shows washi", "start": 1015.649, "duration": 7.151}, {"text": "inexperienced personal version", "start": 1019.7, "duration": 6.46}, {"text": "Katie Tati Pergamum Alex can extend one", "start": 1022.8, "duration": 6.48}, {"text": "ramappa remedies the newness it is the", "start": 1026.16, "duration": 5.76}, {"text": "text and one key across the Jordan", "start": 1029.28, "duration": 5.82}, {"text": "Pederson some revenue than there are", "start": 1031.92, "duration": 7.11}, {"text": "some normal 200 workers at his community", "start": 1035.1, "duration": 8.13}, {"text": "today we travel - Femi tea soda", "start": 1039.03, "duration": 6.84}, {"text": "volcanoes avatar suit support support", "start": 1043.23, "duration": 4.949}, {"text": "dispenser the nationalist dance there is", "start": 1045.87, "duration": 6.72}, {"text": "what review GG Janet Jackson chemotactic", "start": 1048.179, "duration": 7.081}, {"text": "in Moroccan villa stock of coins of", "start": 1052.59, "duration": 5.76}, {"text": "bougie the next M that I sold my next", "start": 1055.26, "duration": 5.299}, {"text": "ahem", "start": 1058.35, "duration": 2.209}, {"text": "weight equal to 1/6 and if they were", "start": 1089.68, "duration": 8.68}, {"text": "mostly she will be thicker", "start": 1096.2, "duration": 4.44}, {"text": "whose stupid such as a person did", "start": 1098.36, "duration": 5.31}, {"text": "shipment me remain yummy and I may avoid", "start": 1100.64, "duration": 4.86}, {"text": "additional recommended from the dead", "start": 1103.67, "duration": 4.29}, {"text": "town get a battery badly yep a Sony", "start": 1105.5, "duration": 4.89}, {"text": "Tablet or Evalia body it can skeet a", "start": 1107.96, "duration": 4.95}, {"text": "conservator it should oppressor epitope", "start": 1110.39, "duration": 6.81}, {"text": "you a big a big person about flag if it", "start": 1112.91, "duration": 7.2}, {"text": "not review and again we need certificate", "start": 1117.2, "duration": 6.21}, {"text": "Wilma DC comic opera Brad we are not on", "start": 1120.11, "duration": 6.06}, {"text": "the kitchen me lemon he only a pelican", "start": 1123.41, "duration": 4.77}, {"text": "ferocity care about you are worsted oil", "start": 1126.17, "duration": 6.42}, {"text": "and the conference epidemic a tear mayor", "start": 1128.18, "duration": 8.21}, {"text": "but Allah was in Syria specifically", "start": 1132.59, "duration": 9.69}, {"text": "policy the zone the metal a metal coated", "start": 1136.39, "duration": 7.12}, {"text": "exactly welcome Logan", "start": 1142.28, "duration": 4.65}, {"text": "meesa meesa sama complement soft when", "start": 1143.51, "duration": 6.51}, {"text": "you san jose-madurai stages accepted to", "start": 1146.93, "duration": 5.52}, {"text": "good amount a disability deeds must", "start": 1150.02, "duration": 4.59}, {"text": "teach with steamers reported back", "start": 1152.45, "duration": 4.71}, {"text": "special few substantial Kenosha emulsion", "start": 1154.61, "duration": 6.86}, {"text": "has issued to mount monk riser a gloved", "start": 1157.16, "duration": 7.649}, {"text": "well-kept a steeple integrity supporters", "start": 1161.47, "duration": 6.01}, {"text": "the community for metalic point it's too", "start": 1164.809, "duration": 8.6}, {"text": "powerful a vasila no no but it's it so", "start": 1167.48, "duration": 5.929}, {"text": "you see a lot of people what's next for", "start": 1174.909, "duration": 14.171}, {"text": "this because it seems like maybe it was", "start": 1187.58, "duration": 5.04}, {"text": "a bit of a like this big event that", "start": 1189.08, "duration": 8.219}, {"text": "happened a lot of attention and I might", "start": 1192.62, "duration": 9.12}, {"text": "be wrong but maybe it's starting to so I", "start": 1197.299, "duration": 6.0}, {"text": "wonder like what do you think has been", "start": 1201.74, "duration": 4.23}, {"text": "at happen next what's the next change in", "start": 1203.299, "duration": 8.1}, {"text": "the culture how are we gonna shake so he", "start": 1205.97, "duration": 7.289}, {"text": "asked what's next he says it did Jordan", "start": 1211.399, "duration": 4.201}, {"text": "Peterson event was a moment and he's", "start": 1213.259, "duration": 3.721}, {"text": "bringing people back to fixing up their", "start": 1215.6, "duration": 3.36}, {"text": "lives I'm back to faith all these things", "start": 1216.98, "duration": 3.84}, {"text": "but he asked what would we do now", "start": 1218.96, "duration": 4.349}, {"text": "because of course it's a wave and the", "start": 1220.82, "duration": 4.5}, {"text": "wave feels like it's kind of going down", "start": 1223.309, "duration": 4.291}, {"text": "although my goodness every time I think", "start": 1225.32, "duration": 3.87}, {"text": "I adjourn jury to speak and then it's", "start": 1227.6, "duration": 3.72}, {"text": "like okay learn more it's like one more", "start": 1229.19, "duration": 4.05}, {"text": "really in the pit anyway but it's true", "start": 1231.32, "duration": 3.27}, {"text": "it's a white it's going to fade it's", "start": 1233.24, "duration": 3.09}, {"text": "just like any phenomena at some point", "start": 1234.59, "duration": 3.689}, {"text": "it's going to reach some height and it's", "start": 1236.33, "duration": 4.979}, {"text": "going to fade and I think that think", "start": 1238.279, "duration": 5.64}, {"text": "that's when that's when we need to take", "start": 1241.309, "duration": 4.71}, {"text": "what you saying the best things of what", "start": 1243.919, "duration": 3.84}, {"text": "we saying to take them at Harvard to", "start": 1246.019, "duration": 4.26}, {"text": "this us now right it's if it's all it's", "start": 1247.759, "duration": 5.37}, {"text": "our job to make our lives better to make", "start": 1250.279, "duration": 4.98}, {"text": "our families better to make our", "start": 1253.129, "duration": 6.93}, {"text": "immediate communities better and work on", "start": 1255.259, "duration": 6.66}, {"text": "that you know and have real", "start": 1260.059, "duration": 4.32}, {"text": "relationships and real and that's that's", "start": 1261.919, "duration": 4.11}, {"text": "the next step because that even that's", "start": 1264.379, "duration": 3.451}, {"text": "what he says is the only thing that's", "start": 1266.029, "duration": 4.11}, {"text": "going to save our culture is if you know", "start": 1267.83, "duration": 3.689}, {"text": "if you take care of the people around", "start": 1270.139, "duration": 3.48}, {"text": "you and you love your neighbor instead", "start": 1271.519, "duration": 4.441}, {"text": "of being on Twitter fighting some you", "start": 1273.619, "duration": 4.17}, {"text": "know and Jordan is guilty", "start": 1275.96, "duration": 3.779}, {"text": "like metier metier mentioned like he's", "start": 1277.789, "duration": 4.47}, {"text": "he he does it and then I mean sometimes", "start": 1279.739, "duration": 5.101}, {"text": "he's told me he said he said okay I have", "start": 1282.259, "duration": 4.74}, {"text": "to his son will take away his Twitter", "start": 1284.84, "duration": 5.279}, {"text": "rights because he guess he just gets", "start": 1286.999, "duration": 5.37}, {"text": "caught up and even myself he thought he", "start": 1290.119, "duration": 4.14}, {"text": "kept telling he's like it says on", "start": 1292.369, "duration": 2.52}, {"text": "Twitter", "start": 1294.259, "duration": 2.64}, {"text": "don't answer anybody that you don't", "start": 1294.889, "duration": 4.201}, {"text": "follow or else you're serious trouble", "start": 1296.899, "duration": 4.23}, {"text": "like just don't do it it's not it just", "start": 1299.09, "duration": 4.11}, {"text": "drags you into these emotions and it's", "start": 1301.129, "duration": 3.691}, {"text": "not worth it and he's not perfect he's", "start": 1303.2, "duration": 3.99}, {"text": "falling into that hole you saw some put", "start": 1304.82, "duration": 5.669}, {"text": "those crazy tweets thank you and so he's", "start": 1307.19, "duration": 4.919}, {"text": "done it himself and and I'm sure if you", "start": 1310.489, "duration": 2.76}, {"text": "ask him he'd be like aw man I can't", "start": 1312.109, "duration": 2.63}, {"text": "believe I did that you know he's very", "start": 1313.249, "duration": 4.11}, {"text": "reasonable in that sense so I think it's", "start": 1314.739, "duration": 6.27}, {"text": "us the only thing I can say", "start": 1317.359, "duration": 3.65}, {"text": "[Music]", "start": 1366.39, "duration": 3.029}, {"text": "- TV ad Jordan take your sumela pretend", "start": 1379.34, "duration": 12.36}, {"text": "that sugar on it", "start": 1387.95, "duration": 3.75}, {"text": "no get show ck sick father said the", "start": 1392.99, "duration": 14.35}, {"text": "sketch were system the photo shows the", "start": 1403.68, "duration": 12.03}, {"text": "possum Kuja confessor is just an act now", "start": 1407.34, "duration": 16.65}, {"text": "to the second Thomas shoal O Matic poor", "start": 1415.71, "duration": 12.03}, {"text": "Maggie - gee sonic new comforter it's", "start": 1423.99, "duration": 7.29}, {"text": "the more cash per tick can stick a Cathy", "start": 1427.74, "duration": 5.7}, {"text": "could see Superman these are ma the", "start": 1431.28, "duration": 4.5}, {"text": "ricotta cake can't trigger", "start": 1433.44, "duration": 6.93}, {"text": "good jello you sign up of work according", "start": 1435.78, "duration": 6.72}, {"text": "this is it jump feet swing it could be", "start": 1440.37, "duration": 4.71}, {"text": "educated when hockey hockey is work", "start": 1442.5, "duration": 5.25}, {"text": "castles the you critical such director", "start": 1445.08, "duration": 4.92}, {"text": "shows he him", "start": 1447.75, "duration": 7.67}, {"text": "Tuesday we see mechanical and treat sick", "start": 1450.0, "duration": 5.42}, {"text": "see through the foreman joke my election", "start": 1459.86, "duration": 6.25}, {"text": "ticket either visa cash but a comics", "start": 1464.16, "duration": 6.69}, {"text": "authenticity daca Rican bath son Daniel", "start": 1466.11, "duration": 8.21}, {"text": "coupe is like a spec cooker yes inside", "start": 1470.85, "duration": 6.39}, {"text": "difficulty on may accept and this is the", "start": 1474.32, "duration": 6.13}, {"text": "electric air she's just put a cop - yes", "start": 1477.24, "duration": 5.52}, {"text": "- Tenzin - Akio do you can see a nice", "start": 1480.45, "duration": 6.42}, {"text": "fish it's coffee cup or she said it if", "start": 1482.76, "duration": 5.73}, {"text": "something that's Pentecost Monday on", "start": 1486.87, "duration": 4.2}, {"text": "this bizarre case past Kemal the postman", "start": 1488.49, "duration": 6.65}, {"text": "is your pleasure to chose GTD focused on", "start": 1491.07, "duration": 6.32}, {"text": "TC a second opinion", "start": 1495.14, "duration": 5.95}, {"text": "kisses potaka maipi skills ski geniality", "start": 1497.39, "duration": 7.6}, {"text": "glory seeker see connect much it isn't a", "start": 1501.09, "duration": 7.17}, {"text": "motion to attempt the it's a cheap cheap", "start": 1504.99, "duration": 5.4}, {"text": "it'll do a big rebel wisdom which it", "start": 1508.26, "duration": 4.58}, {"text": "dissipate your fears and the heretic", "start": 1510.39, "duration": 4.98}, {"text": "allergic John just exist at the time and", "start": 1512.84, "duration": 5.02}, {"text": "it takes the puts to get a device watch", "start": 1515.37, "duration": 4.2}, {"text": "I'm going to divide Jordan today Jordan", "start": 1517.86, "duration": 3.75}, {"text": "here's me calling your hair take ha ha", "start": 1519.57, "duration": 3.54}, {"text": "ha", "start": 1521.61, "duration": 3.33}, {"text": "that's when one certification went on", "start": 1523.11, "duration": 4.17}, {"text": "any Apocrypha that guard existing you", "start": 1524.94, "duration": 4.71}, {"text": "really perform of war that's catalytic", "start": 1527.28, "duration": 5.25}, {"text": "up you bleep take see sister so cities", "start": 1529.65, "duration": 4.89}, {"text": "and yeah shows ketchup listen Tuesday", "start": 1532.53, "duration": 4.17}, {"text": "take care magnetic as per the amount", "start": 1534.54, "duration": 5.25}, {"text": "amount research looks at another come to", "start": 1536.7, "duration": 5.04}, {"text": "us when I meet a porn web he come are", "start": 1539.79, "duration": 4.08}, {"text": "not forgotten Elsa get the service have", "start": 1541.74, "duration": 4.47}, {"text": "a perfect is on empty havoc Jordan the", "start": 1543.87, "duration": 5.87}, {"text": "cervix is occasionally", "start": 1546.21, "duration": 3.53}, {"text": "[Music]", "start": 1558.54, "duration": 3.039}, {"text": "but aa non-sexual Isaac now the waka", "start": 1594.48, "duration": 8.65}, {"text": "Japan new PowerPoint 602 on a church", "start": 1599.02, "duration": 12.26}, {"text": "possibly possibly curses so security", "start": 1603.13, "duration": 11.52}, {"text": ": balaclava make special because it's up", "start": 1611.28, "duration": 7.57}, {"text": "Yan Yan me Baskar city so the term", "start": 1614.65, "duration": 7.47}, {"text": "recruited the other problem da the zone", "start": 1618.85, "duration": 6.21}, {"text": "Lakota response acute totally this is a", "start": 1622.12, "duration": 5.07}, {"text": "temple Suki Suki of amid dukes with you", "start": 1625.06, "duration": 3.99}, {"text": "first meet the rest in the same beliefs", "start": 1627.19, "duration": 3.9}, {"text": "assessment area sleepless Suzuki", "start": 1629.05, "duration": 4.25}, {"text": "mechanically at Jordan she said visual", "start": 1631.09, "duration": 4.68}, {"text": "sense a capacity the world among", "start": 1633.3, "duration": 6.61}, {"text": "advocate is to regard aluminum", "start": 1635.77, "duration": 5.73}, {"text": "acceptance to through the compound", "start": 1639.91, "duration": 3.9}, {"text": "Kumasi scripture escape air versus Akeno", "start": 1641.5, "duration": 5.34}, {"text": "axially very respected local tea party", "start": 1643.81, "duration": 6.09}, {"text": "and all the al-aqsa supposably", "start": 1646.84, "duration": 5.49}, {"text": "may I meant that this must be done", "start": 1649.9, "duration": 7.29}, {"text": "suppose the document I'll support those", "start": 1652.33, "duration": 7.71}, {"text": "key to dish the garbage ket maysa from", "start": 1657.19, "duration": 5.09}, {"text": "one", "start": 1660.04, "duration": 2.24}, {"text": "well I know for a fact that Jordan", "start": 1665.51, "duration": 4.42}, {"text": "Peterson stances is such that that", "start": 1668.43, "duration": 3.75}, {"text": "differs depending on how people view him", "start": 1669.93, "duration": 5.34}, {"text": "as an individual but I do believe that", "start": 1672.18, "duration": 6.24}, {"text": "Jordan Peterson's stance kind of tends", "start": 1675.27, "duration": 6.81}, {"text": "towards understanding that in politics", "start": 1678.42, "duration": 5.55}, {"text": "or in the political spectrum that", "start": 1682.08, "duration": 3.18}, {"text": "there's people out there in the world", "start": 1683.97, "duration": 3.75}, {"text": "that want to go over in the top of the", "start": 1685.26, "duration": 4.17}, {"text": "biking man in the community for other", "start": 1687.72, "duration": 3.72}, {"text": "individuals so that people cannot freely", "start": 1689.43, "duration": 3.78}, {"text": "express themselves or identify", "start": 1691.44, "duration": 3.15}, {"text": "themselves in a certain manner without", "start": 1693.21, "duration": 2.91}, {"text": "them having to go through some form of", "start": 1694.59, "duration": 7.98}, {"text": "conflict or some type of law sorry", "start": 1696.12, "duration": 8.73}, {"text": "aggression a to suffer some sort towards", "start": 1702.57, "duration": 3.96}, {"text": "a certain group right the monetize", "start": 1704.85, "duration": 4.14}, {"text": "movement and I think that that's what he", "start": 1706.53, "duration": 4.95}, {"text": "is fighting for in my opinion so I want", "start": 1708.99, "duration": 5.13}, {"text": "to ask you right there's a movie that's", "start": 1711.48, "duration": 4.14}, {"text": "coming out you will hurt you're out of", "start": 1714.12, "duration": 2.88}, {"text": "the joke a movie that's coming out right", "start": 1715.62, "duration": 3.36}, {"text": "you've heard that there are people that", "start": 1717.0, "duration": 4.14}, {"text": "are not necessarily feeling a certain", "start": 1718.98, "duration": 3.84}, {"text": "way about the movie due to the fact that", "start": 1721.14, "duration": 3.57}, {"text": "it's so clear they bother and it", "start": 1722.82, "duration": 3.72}, {"text": "encourages certain people on a certain", "start": 1724.71, "duration": 5.58}, {"text": "side to view that particular movie in a", "start": 1726.54, "duration": 5.43}, {"text": "way that's opposed encourage them to do", "start": 1730.29, "duration": 2.85}, {"text": "the exact same thing that's happening", "start": 1731.97, "duration": 4.59}, {"text": "within that amount of the movie but do", "start": 1733.14, "duration": 6.51}, {"text": "you believe that people are more than", "start": 1736.56, "duration": 5.28}, {"text": "capable of trying to follow something", "start": 1739.65, "duration": 3.75}, {"text": "like that as if it's like a blueprint", "start": 1741.84, "duration": 5.04}, {"text": "yeah so he asked well I mean he said", "start": 1743.4, "duration": 4.83}, {"text": "something about nobody ended up asking", "start": 1746.88, "duration": 4.14}, {"text": "about the dobra movie and what I think", "start": 1748.23, "duration": 4.32}, {"text": "in terms of how there's this crazy", "start": 1751.02, "duration": 4.23}, {"text": "reaction to the Joker movie and how it's", "start": 1752.55, "duration": 3.96}, {"text": "going to be a blueprint for certain", "start": 1755.25, "duration": 3.15}, {"text": "people to act a certain way I think it's", "start": 1756.51, "duration": 4.62}, {"text": "hilarious I mean I think it's I'm sorry", "start": 1758.4, "duration": 5.67}, {"text": "I think it's funny because it just came", "start": 1761.13, "duration": 6.049}, {"text": "out like two weeks ago", "start": 1764.07, "duration": 4.88}, {"text": "they're not about a clown that killed", "start": 1767.179, "duration": 3.901}, {"text": "children and then two weeks later", "start": 1768.95, "duration": 5.219}, {"text": "there's this Joker movie but now this is", "start": 1771.08, "duration": 5.399}, {"text": "the movie that is being targeted it's", "start": 1774.169, "duration": 4.14}, {"text": "there's a I haven't seen the movie I'm", "start": 1776.479, "duration": 4.53}, {"text": "gonna go see it for sure now for sure", "start": 1778.309, "duration": 5.1}, {"text": "we'll see it and I might do I might do a", "start": 1781.009, "duration": 4.321}, {"text": "YouTube interpretation of it because I'm", "start": 1783.409, "duration": 3.39}, {"text": "trying to understand what is what is", "start": 1785.33, "duration": 3.509}, {"text": "happening in the culture so that this", "start": 1786.799, "duration": 4.83}, {"text": "movie was targeted for this kind of", "start": 1788.839, "duration": 4.17}, {"text": "weird political pressure that we're", "start": 1791.629, "duration": 3.03}, {"text": "seeing it's very strange I think it's", "start": 1793.009, "duration": 2.73}, {"text": "quite funny that you mention about the", "start": 1794.659, "duration": 2.97}, {"text": "if it would be because I've also heard", "start": 1795.739, "duration": 5.79}, {"text": "that somebody made a post about a", "start": 1797.629, "duration": 7.311}, {"text": "trigger warning for those who are of the", "start": 1801.529, "duration": 6.21}, {"text": "LGBT community right specifically those", "start": 1804.94, "duration": 5.5}, {"text": "in the I guess L of the G right due to", "start": 1807.739, "duration": 4.29}, {"text": "the fact that a gay couple in the MU", "start": 1810.44, "duration": 3.929}, {"text": "chapter 2 got hurt in a certain way okay", "start": 1812.029, "duration": 3.661}, {"text": "and they said that it was traumatizing", "start": 1814.369, "duration": 3.78}, {"text": "so if anybody feels a certain way they", "start": 1815.69, "duration": 3.869}, {"text": "shouldn't watch the movie because of", "start": 1818.149, "duration": 3.71}, {"text": "that", "start": 1819.559, "duration": 2.3}, {"text": "he asks about these political leanings", "start": 1875.089, "duration": 5.53}, {"text": "of the people who made the movie and he", "start": 1878.189, "duration": 4.8}, {"text": "wonders if it had tinged the movie and", "start": 1880.619, "duration": 5.37}, {"text": "whether or not you know because there's", "start": 1882.989, "duration": 4.86}, {"text": "a lot of other people besides ordinary", "start": 1885.989, "duration": 3.63}, {"text": "and everything I mean that they're I", "start": 1887.849, "duration": 5.19}, {"text": "mean they might watch this movie so I'm", "start": 1889.619, "duration": 5.55}, {"text": "gonna say Patricia and I mean they're", "start": 1893.039, "duration": 4.83}, {"text": "just regular left-leaning artistic types", "start": 1895.169, "duration": 5.76}, {"text": "from Toronto Patricia was new Jordan", "start": 1897.869, "duration": 5.04}, {"text": "from before and she got they got all", "start": 1900.929, "duration": 4.65}, {"text": "caught up in this and so they they're", "start": 1902.909, "duration": 5.64}, {"text": "trying to figure it out on for", "start": 1905.579, "duration": 4.44}, {"text": "themselves as well like where do they", "start": 1908.549, "duration": 3.17}, {"text": "stand in terms of kind of these", "start": 1910.019, "duration": 4.47}, {"text": "left-leaning people in this question of", "start": 1911.719, "duration": 4.24}, {"text": "free speech and this question of Jordan", "start": 1914.489, "duration": 2.97}, {"text": "because they obviously like him to", "start": 1915.959, "duration": 2.52}, {"text": "admire him but they're trying to", "start": 1917.459, "duration": 3.12}, {"text": "understand it so so yeah they do have", "start": 1918.479, "duration": 5.3}, {"text": "their own political leanings but um I", "start": 1920.579, "duration": 5.55}, {"text": "don't think another I don't think that", "start": 1923.779, "duration": 3.85}, {"text": "another version of this movie could have", "start": 1926.129, "duration": 4.26}, {"text": "been made and it would be playing in", "start": 1927.629, "duration": 4.98}, {"text": "theaters this movie is already being", "start": 1930.389, "duration": 5.471}, {"text": "shut down so if any other type of movie", "start": 1932.609, "duration": 20.021}, {"text": "and made oh my goodness so he has as", "start": 1935.86, "duration": 18.39}, {"text": "someone who's been in technology record", "start": 1952.63, "duration": 6.0}, {"text": "is still he is symbology what would I do", "start": 1954.25, "duration": 7.08}, {"text": "Jordan warrant against doing that he", "start": 1958.63, "duration": 4.41}, {"text": "said several times that you never should", "start": 1961.33, "duration": 3.93}, {"text": "become an architect because it'll kill", "start": 1963.04, "duration": 6.45}, {"text": "you I have said several times that I", "start": 1965.26, "duration": 7.14}, {"text": "think that Jordan is a and I say that in", "start": 1969.49, "duration": 5.069}, {"text": "the movie as well that he's an", "start": 1972.4, "duration": 4.95}, {"text": "in-between figure and that's why he's", "start": 1974.559, "duration": 5.461}, {"text": "receiving all the scorn from both sides", "start": 1977.35, "duration": 6.84}, {"text": "right so he doesn't fit he's kind of", "start": 1980.02, "duration": 6.39}, {"text": "like this strange figure I've said he's", "start": 1984.19, "duration": 4.14}, {"text": "something like I like John the Baptist", "start": 1986.41, "duration": 7.68}, {"text": "or or someone like Elijah these weird", "start": 1988.33, "duration": 8.52}, {"text": "figure that are kind of out of place and", "start": 1994.09, "duration": 4.469}, {"text": "and there's telling everybody pay", "start": 1996.85, "duration": 4.37}, {"text": "attention pay attention you know", "start": 1998.559, "duration": 6.601}, {"text": "Elijah's Elijah's Georgia started st.", "start": 2001.22, "duration": 5.92}, {"text": "John the Baptist Maine saying was you", "start": 2005.16, "duration": 3.87}, {"text": "know it's usually like the voice crying", "start": 2007.14, "duration": 4.14}, {"text": "out in the wilderness right make", "start": 2009.03, "duration": 4.05}, {"text": "straight the waves for the Lord", "start": 2011.28, "duration": 3.6}, {"text": "it's basically saying clean your room", "start": 2013.08, "duration": 5.729}, {"text": "that's the thing tell the guys the", "start": 2014.88, "duration": 6.24}, {"text": "things in your room right so that", "start": 2018.809, "duration": 4.74}, {"text": "something bigger could happen and so", "start": 2021.12, "duration": 5.04}, {"text": "that if I would reduce drug Peterson to", "start": 2023.549, "duration": 4.441}, {"text": "one thing I would say he's kind of a", "start": 2026.16, "duration": 7.19}, {"text": "weird John the Baptist figure weird", "start": 2027.99, "duration": 5.36}, {"text": "so he asked if I was worried that", "start": 2043.84, "duration": 6.16}, {"text": "something would happen here no I was not", "start": 2046.639, "duration": 5.01}, {"text": "worried that something would happen here", "start": 2050.0, "duration": 5.19}, {"text": "and the reason why I was not worried is", "start": 2051.649, "duration": 6.45}, {"text": "because George is not that known here", "start": 2055.19, "duration": 4.77}, {"text": "do you notice he didn't come to Montreal", "start": 2058.099, "duration": 4.02}, {"text": "on his death of rules for the pitch what", "start": 2059.96, "duration": 4.469}, {"text": "lose but I francophone culture has not", "start": 2062.119, "duration": 5.76}, {"text": "really kind of seen him on the horizon", "start": 2064.429, "duration": 5.49}, {"text": "so I think that that he has too little", "start": 2067.879, "duration": 7.861}, {"text": "attention to draw any higher in yeah I", "start": 2069.919, "duration": 7.141}, {"text": "thought it was just because of the fact", "start": 2075.74, "duration": 5.21}, {"text": "that this is more of me I would say", "start": 2077.06, "duration": 6.029}, {"text": "someone more than a conservative type", "start": 2080.95, "duration": 4.389}, {"text": "where that Ontario especially Toronto's", "start": 2083.089, "duration": 4.881}, {"text": "more liberal", "start": 2085.339, "duration": 2.631}, {"text": "yes why I think Jordan is not picking up", "start": 2097.12, "duration": 4.75}, {"text": "with our Quebec francophone culture I", "start": 2100.01, "duration": 4.77}, {"text": "think one of the reasons is because a", "start": 2101.87, "duration": 5.61}, {"text": "lot of the a lot of the kind of crazy", "start": 2104.78, "duration": 4.92}, {"text": "postmodern stuff like they're really", "start": 2107.48, "duration": 5.31}, {"text": "really intense it's just not cured at", "start": 2109.7, "duration": 6.15}, {"text": "least not yet so there's some inkling of", "start": 2112.79, "duration": 5.01}, {"text": "it we see it a little bit but it's not", "start": 2115.85, "duration": 5.45}, {"text": "it's not this massive it's not a massive", "start": 2117.8, "duration": 6.12}, {"text": "in Quebec so I think that a lot of the", "start": 2121.3, "duration": 4.72}, {"text": "things that Jordan ders is saying at", "start": 2123.92, "duration": 5.1}, {"text": "least for now it's not really resonating", "start": 2126.02, "duration": 4.59}, {"text": "because we don't have it as much here", "start": 2129.02, "duration": 4.55}, {"text": "that's my perception", "start": 2130.61, "duration": 2.96}, {"text": "[Music]", "start": 2139.52, "duration": 3.039}, {"text": "janaka's see Jordan they see getting my", "start": 2152.7, "duration": 6.309}, {"text": "job back and he said what what she might", "start": 2155.349, "duration": 5.67}, {"text": "say today missus just be your book you", "start": 2159.009, "duration": 4.77}, {"text": "put that down show me see the muscle", "start": 2161.019, "duration": 5.131}, {"text": "it's only the 12 rules for life Afghan", "start": 2163.779, "duration": 5.721}, {"text": "says you cut school about", "start": 2166.15, "duration": 3.35}, {"text": "so he asks if he's working but yeah yes", "start": 2182.78, "duration": 6.45}, {"text": "yeah he he he wrote if you know the 12", "start": 2185.57, "duration": 6.24}, {"text": "rules for thy book was a condensation of", "start": 2189.23, "duration": 5.37}, {"text": "an answer that he wrote on Quora and it", "start": 2191.81, "duration": 4.02}, {"text": "was that it was like kind of", "start": 2194.6, "duration": 3.18}, {"text": "40-something answer it's like 50 antes", "start": 2195.83, "duration": 3.66}, {"text": "or something and so he's gonna write", "start": 2197.78, "duration": 3.48}, {"text": "he's just going to take those other a", "start": 2199.49, "duration": 3.78}, {"text": "lot of those other rules that he that he", "start": 2201.26, "duration": 4.29}, {"text": "wanted to talk about and make a like a", "start": 2203.27, "duration": 16.65}, {"text": "CEO of his worldview or view the world", "start": 2205.55, "duration": 17.28}, {"text": "like that I think he has like this idea", "start": 2219.92, "duration": 6.9}, {"text": "in terms of purpose like that he's kind", "start": 2222.83, "duration": 7.05}, {"text": "of intuition based like your ideal and", "start": 2226.82, "duration": 5.85}, {"text": "you will kind of you should you know", "start": 2229.88, "duration": 5.489}, {"text": "what you should do yeah and I think one", "start": 2232.67, "duration": 4.77}, {"text": "time he said you know kind of follow", "start": 2235.369, "duration": 4.801}, {"text": "that ideal unless you have the level of", "start": 2237.44, "duration": 5.179}, {"text": "bottom", "start": 2240.17, "duration": 2.449}, {"text": "so he's asking me what I think is", "start": 2245.83, "duration": 6.67}, {"text": "missing in George Peterson I think that", "start": 2248.45, "duration": 10.37}, {"text": "I think that because Jordan is is so", "start": 2252.5, "duration": 9.26}, {"text": "worried about totalitarian thought", "start": 2258.82, "duration": 5.47}, {"text": "because he's so wary of totalitarian", "start": 2261.76, "duration": 4.45}, {"text": "thought he really focus on the", "start": 2264.29, "duration": 4.89}, {"text": "individualism and the danger of that is", "start": 2266.21, "duration": 4.26}, {"text": "that it can become that can become", "start": 2269.18, "duration": 3.57}, {"text": "individualism and we've had enough", "start": 2270.47, "duration": 4.08}, {"text": "individualism in the world right you've", "start": 2272.75, "duration": 3.78}, {"text": "had enough of fragmented individuals who", "start": 2274.55, "duration": 3.48}, {"text": "just are on their own and I know that's", "start": 2276.53, "duration": 3.42}, {"text": "not what you wanted and I know I don't", "start": 2278.03, "duration": 3.27}, {"text": "want you distorted message I know that's", "start": 2279.95, "duration": 4.44}, {"text": "not what you want but sometimes he will", "start": 2281.3, "duration": 6.24}, {"text": "point to the fact that this is these", "start": 2284.39, "duration": 5.19}, {"text": "communions of individuals it has to", "start": 2287.54, "duration": 4.91}, {"text": "scale up it has to scale up into", "start": 2289.58, "duration": 5.76}, {"text": "communities and scale up into something", "start": 2292.45, "duration": 8.02}, {"text": "more right and so the difficulty of that", "start": 2295.34, "duration": 7.26}, {"text": "is that that does end up looking", "start": 2300.47, "duration": 5.88}, {"text": "something like identity now the question", "start": 2302.6, "duration": 5.85}, {"text": "is how do we do that so that it's not", "start": 2306.35, "duration": 5.91}, {"text": "dangerous and that it's not toxic how", "start": 2308.45, "duration": 7.98}, {"text": "can we create communion without the", "start": 2312.26, "duration": 5.7}, {"text": "danger of the tough the totalitarian", "start": 2316.43, "duration": 3.21}, {"text": "extreme and I think that that's", "start": 2317.96, "duration": 3.99}, {"text": "something that he doesn't really talk", "start": 2319.64, "duration": 4.8}, {"text": "about a lot and so I mean obviously I", "start": 2321.95, "duration": 4.68}, {"text": "think I come from my own side I I", "start": 2324.44, "duration": 4.02}, {"text": "believe that that's what when they did", "start": 2326.63, "duration": 4.68}, {"text": "did and he says that too right he says", "start": 2328.46, "duration": 4.23}, {"text": "that that too that would that's what", "start": 2331.31, "duration": 3.6}, {"text": "religion used to do but he's not willing", "start": 2332.69, "duration": 4.68}, {"text": "to like he doesn't want to say that it", "start": 2334.91, "duration": 4.98}, {"text": "still could still be possible and that", "start": 2337.37, "duration": 4.62}, {"text": "made for me that's the big that's the", "start": 2339.89, "duration": 5.03}, {"text": "big gap I would say", "start": 2341.99, "duration": 2.93}, {"text": "individualism yeah that is exactly", "start": 2347.369, "duration": 23.621}, {"text": "that's exactly the way that he frames it", "start": 2368.98, "duration": 3.81}, {"text": "and I think that there's some value to", "start": 2370.99, "duration": 3.36}, {"text": "that which is he's saying I'm not", "start": 2372.79, "duration": 4.59}, {"text": "telling people individuals that they", "start": 2374.35, "duration": 6.12}, {"text": "have to take on all on themselves that", "start": 2377.38, "duration": 4.68}, {"text": "they have to take on the responsibility", "start": 2380.47, "duration": 4.56}, {"text": "on themselves and not you know not focus", "start": 2382.06, "duration": 4.799}, {"text": "on their rights and their privileges and", "start": 2385.03, "duration": 4.71}, {"text": "I agree but I still need I still don't", "start": 2386.859, "duration": 6.081}, {"text": "see how in his system it scales up I", "start": 2389.74, "duration": 8.81}, {"text": "mean I think it does but yeah", "start": 2392.94, "duration": 5.61}, {"text": "whether it is he would take his message", "start": 2413.17, "duration": 5.28}, {"text": "board to the main shipping culture like", "start": 2416.2, "duration": 4.5}, {"text": "honey West tweeted about computers and", "start": 2418.45, "duration": 14.18}, {"text": "haven't like waiting for impossible very", "start": 2420.7, "duration": 22.14}, {"text": "political yeah no III think that he's", "start": 2432.63, "duration": 12.22}, {"text": "all he would definitely do that for sure", "start": 2442.84, "duration": 3.3}, {"text": "I mean he's sold three million books", "start": 2444.85, "duration": 3.78}, {"text": "that's not that's not an academic level", "start": 2446.14, "duration": 9.03}, {"text": "of discussion that's like to have a", "start": 2448.63, "duration": 8.49}, {"text": "Kanye West or infinity I'm waiting for", "start": 2455.17, "duration": 4.56}, {"text": "them I've been waiting for I've been", "start": 2457.12, "duration": 4.86}, {"text": "waiting for that interview from before I", "start": 2459.73, "duration": 3.96}, {"text": "did Gordon sorry I've been waiting for a", "start": 2461.98, "duration": 3.95}, {"text": "kind", "start": 2463.69, "duration": 2.24}, {"text": "all right maybe yeah harder for me this", "start": 2470.81, "duration": 10.69}, {"text": "hardening was the senior professor who", "start": 2478.59, "duration": 5.49}, {"text": "wrote the article yeah I think becoming", "start": 2481.5, "duration": 6.03}, {"text": "a dangerous be here more than that it", "start": 2484.08, "duration": 5.37}, {"text": "was when he said that Jordan was trying", "start": 2487.53, "duration": 6.2}, {"text": "to reach out multiple times", "start": 2489.45, "duration": 4.28}, {"text": "do you think that most people received", "start": 2498.24, "duration": 4.619}, {"text": "or it appears that someone who wasn't", "start": 2501.18, "duration": 4.08}, {"text": "genuinely have we debated conversations", "start": 2502.859, "duration": 6.951}, {"text": "with them or is just someone who's just", "start": 2505.26, "duration": 4.55}, {"text": "listening so he says the discovery was", "start": 2509.93, "duration": 8.71}, {"text": "disheartening part was the part when his", "start": 2515.609, "duration": 5.671}, {"text": "friend wrote that article and then", "start": 2518.64, "duration": 4.35}, {"text": "wasn't going to take towards calls", "start": 2521.28, "duration": 3.15}, {"text": "despite the fact Iran is calling on", "start": 2522.99, "duration": 3.81}, {"text": "comi\u00f3 they asked about how people", "start": 2524.43, "duration": 3.36}, {"text": "perceive I mean I don't know how people", "start": 2526.8, "duration": 3.51}, {"text": "perceive your inclusive for sure I think", "start": 2527.79, "duration": 5.88}, {"text": "that like I said my experience of him is", "start": 2530.31, "duration": 4.32}, {"text": "that he's the real deal", "start": 2533.67, "duration": 2.79}, {"text": "like he's what you see he's not", "start": 2534.63, "duration": 4.38}, {"text": "pretending he wants he wants to have as", "start": 2536.46, "duration": 5.28}, {"text": "much real contact that when he's like he", "start": 2539.01, "duration": 5.73}, {"text": "tears up he's not it's not theater he's", "start": 2541.74, "duration": 4.92}, {"text": "he's actually genuinely touched by", "start": 2544.74, "duration": 4.47}, {"text": "whatever effect he's able to have and to", "start": 2546.66, "duration": 4.02}, {"text": "see people get their lives together and", "start": 2549.21, "duration": 3.24}, {"text": "to see people mend their relationships", "start": 2550.68, "duration": 4.439}, {"text": "and that's like he's he's he really", "start": 2552.45, "duration": 6.6}, {"text": "wants that to happen so people that", "start": 2555.119, "duration": 6.601}, {"text": "don't like him in there that are that", "start": 2559.05, "duration": 4.62}, {"text": "have already made up their minds at this", "start": 2561.72, "duration": 3.84}, {"text": "point I don't think they're gonna change", "start": 2563.67, "duration": 3.3}, {"text": "I don't think they're gonna change their", "start": 2565.56, "duration": 3.45}, {"text": "mind and Jordan has been saying now for", "start": 2566.97, "duration": 4.35}, {"text": "a year that he means he wants to stop", "start": 2569.01, "duration": 4.98}, {"text": "doing interviews just because it's so", "start": 2571.32, "duration": 4.59}, {"text": "exhausting you guys won't realize like", "start": 2573.99, "duration": 3.57}, {"text": "when he does an interview with that like", "start": 2575.91, "duration": 3.179}, {"text": "the committee does one of those", "start": 2577.56, "duration": 2.97}, {"text": "interviews like that french guy that you", "start": 2579.089, "duration": 3.181}, {"text": "saw and they never you like just how", "start": 2580.53, "duration": 4.05}, {"text": "arrogant he is and kind of like and", "start": 2582.27, "duration": 5.339}, {"text": "Jordan is out three days after that cuz", "start": 2584.58, "duration": 5.1}, {"text": "he just he doesn't want that he doesn't", "start": 2587.609, "duration": 3.99}, {"text": "like that he hates it he hates", "start": 2589.68, "duration": 4.29}, {"text": "these kind of conflictual conversations", "start": 2591.599, "duration": 3.99}, {"text": "people think that he's looking for them", "start": 2593.97, "duration": 3.0}, {"text": "that he someone gets a rise out of this", "start": 2595.589, "duration": 4.321}, {"text": "conflict he despised him and so when he", "start": 2596.97, "duration": 4.86}, {"text": "has to face this thing he's gonna face", "start": 2599.91, "duration": 3.929}, {"text": "it but then it like it just it just", "start": 2601.83, "duration": 3.24}, {"text": "Wrexham and so", "start": 2603.839, "duration": 2.911}, {"text": "he's been even saying that he wants to", "start": 2605.07, "duration": 3.69}, {"text": "get away from that for a while I don't", "start": 2606.75, "duration": 15.78}, {"text": "they'll be able to say says one of the", "start": 2608.76, "duration": 15.36}, {"text": "biggest criticisms of Jorn is that he's", "start": 2622.53, "duration": 2.91}, {"text": "a bit of a Rorschach test", "start": 2624.12, "duration": 3.72}, {"text": "and what's my thought about that I I", "start": 2625.44, "duration": 4.11}, {"text": "think that you're I think that you're", "start": 2627.84, "duration": 4.5}, {"text": "not totally wrong I think that that's", "start": 2629.55, "duration": 4.86}, {"text": "one of that's what it one of those", "start": 2632.34, "duration": 4.26}, {"text": "that's what an intermediary character is", "start": 2634.41, "duration": 5.28}, {"text": "the intermediary character is a", "start": 2636.6, "duration": 5.28}, {"text": "character that isn't totally defined and", "start": 2639.69, "duration": 4.41}, {"text": "you project into that character and", "start": 2641.88, "duration": 4.14}, {"text": "that's why people are projected into him", "start": 2644.1, "duration": 3.96}, {"text": "because it's crazy it's like the type of", "start": 2646.02, "duration": 4.38}, {"text": "things people are saying you know I know", "start": 2648.06, "duration": 4.11}, {"text": "people that have told me you know", "start": 2650.4, "duration": 3.99}, {"text": "extreme right people who regularly", "start": 2652.17, "duration": 3.84}, {"text": "people who write me and say how can you", "start": 2654.39, "duration": 3.09}, {"text": "even talk to him", "start": 2656.01, "duration": 4.95}, {"text": "he's a he's a globalist he's a show he's", "start": 2657.48, "duration": 5.46}, {"text": "an Illuminati he's you know he's all", "start": 2660.96, "duration": 4.86}, {"text": "that then and then someone else is", "start": 2662.94, "duration": 6.39}, {"text": "saying that he's a Nazi that he's you", "start": 2665.82, "duration": 5.25}, {"text": "know that he's a horrible misogynist", "start": 2669.33, "duration": 3.57}, {"text": "racist all this stuff so it's like how", "start": 2671.07, "duration": 3.87}, {"text": "can he be fits to extremes at the same", "start": 2672.9, "duration": 4.02}, {"text": "time but that's the thing that's that's", "start": 2674.94, "duration": 5.7}, {"text": "why he's attracting that a program", "start": 2676.92, "duration": 5.13}, {"text": "that's why he's attracting that because", "start": 2680.64, "duration": 3.9}, {"text": "he has he is this weird intermediary", "start": 2682.05, "duration": 5.37}, {"text": "character and so he is a Rorschach test", "start": 2684.54, "duration": 5.99}, {"text": "I agree I agree", "start": 2687.42, "duration": 3.11}, {"text": "that's what I feel that is quite intense", "start": 2694.01, "duration": 5.64}, {"text": "and it does loosen and authentic that's", "start": 2697.49, "duration": 5.07}, {"text": "what I get out of him sometimes I've", "start": 2699.65, "duration": 4.2}, {"text": "seen it with some interviews in that and", "start": 2702.56, "duration": 2.88}, {"text": "thinking you're so smart man and you", "start": 2703.85, "duration": 4.11}, {"text": "know this gothic just break it down he", "start": 2705.44, "duration": 3.93}, {"text": "doesn't break it down my mind sometimes", "start": 2707.96, "duration": 4.02}, {"text": "it doesn't know I would receive he", "start": 2709.37, "duration": 4.65}, {"text": "doesn't know how to close the gap he", "start": 2711.98, "duration": 5.1}, {"text": "knows the other person is he's going off", "start": 2714.02, "duration": 20.88}, {"text": "of it or like yes yeah yes sir she says", "start": 2717.08, "duration": 19.02}, {"text": "she says sometimes you see them in", "start": 2734.9, "duration": 3.63}, {"text": "interviews and she feels like he", "start": 2736.1, "duration": 4.05}, {"text": "couldn't connect things like you", "start": 2738.53, "duration": 3.24}, {"text": "couldn't he could he could bring things", "start": 2740.15, "duration": 2.97}, {"text": "together but that he doesn't they be", "start": 2741.77, "duration": 4.05}, {"text": "smart that he should and he doesn't and", "start": 2743.12, "duration": 5.97}, {"text": "it's you know all I can say about that", "start": 2745.82, "duration": 6.48}, {"text": "is how many of us have ever been in a", "start": 2749.09, "duration": 4.65}, {"text": "public discussion where someone is", "start": 2752.3, "duration": 4.29}, {"text": "attacking like I have never been in that", "start": 2753.74, "duration": 5.85}, {"text": "situation you know where you're on air", "start": 2756.59, "duration": 4.29}, {"text": "you know there's gonna be a million", "start": 2759.59, "duration": 3.18}, {"text": "people watching and now the person is", "start": 2760.88, "duration": 4.02}, {"text": "going after you it's like how do you", "start": 2762.77, "duration": 5.58}, {"text": "even react to that so I think that a lot", "start": 2764.9, "duration": 5.22}, {"text": "of it is that is just trying to stay", "start": 2768.35, "duration": 4.02}, {"text": "cool just think oh my goodness", "start": 2770.12, "duration": 4.47}, {"text": "it's like it doesn't get angry a lot I", "start": 2772.37, "duration": 3.36}, {"text": "would you know you could imagine just", "start": 2774.59, "duration": 2.7}, {"text": "just saying this is it", "start": 2775.73, "duration": 3.0}, {"text": "this is what this interview is done to", "start": 2777.29, "duration": 3.09}, {"text": "you bad intentions I'm out of here", "start": 2778.73, "duration": 4.92}, {"text": "it's like but so so I think a lot of it", "start": 2780.38, "duration": 8.48}, {"text": "is that it's just just tough yeah maybe", "start": 2783.65, "duration": 5.21}, {"text": "and how holy perceive that community as", "start": 2792.06, "duration": 7.09}, {"text": "we often do straight so there's this", "start": 2795.79, "duration": 5.82}, {"text": "multi-dimensional phenomena that is", "start": 2799.15, "duration": 9.0}, {"text": "tradition where you have and then you", "start": 2801.61, "duration": 9.12}, {"text": "have the person was just trying to be", "start": 2808.15, "duration": 6.09}, {"text": "true to his balance and sometimes it's", "start": 2810.73, "duration": 6.27}, {"text": "gone you know I was thinking and you're", "start": 2814.24, "duration": 6.24}, {"text": "saying what we're seeing is that he had", "start": 2817.0, "duration": 6.81}, {"text": "this fight that's going for him again", "start": 2820.48, "duration": 6.51}, {"text": "like what is again a student species for", "start": 2823.81, "duration": 5.91}, {"text": "within speech and that's what the grass", "start": 2826.99, "duration": 5.88}, {"text": "means getting focused on right but I", "start": 2829.72, "duration": 4.77}, {"text": "sort of appreciate use to believe that", "start": 2832.87, "duration": 6.15}, {"text": "all his other aspects one of which is", "start": 2834.49, "duration": 7.38}, {"text": "book about bettering yourself generate", "start": 2839.02, "duration": 5.43}, {"text": "across to that community and if it does", "start": 2841.87, "duration": 4.85}, {"text": "why", "start": 2844.45, "duration": 2.27}, {"text": "oh so he says that he feels like after", "start": 2846.96, "duration": 8.49}, {"text": "Friday can then 27th he said it feels", "start": 2852.96, "duration": 5.22}, {"text": "like that often now it's presented that", "start": 2855.45, "duration": 4.62}, {"text": "he's talking it seems like it's against", "start": 2858.18, "duration": 3.15}, {"text": "the trans community but that there are", "start": 2860.07, "duration": 2.67}, {"text": "all these complex", "start": 2861.33, "duration": 3.99}, {"text": "he's a very multifaceted figure you know", "start": 2862.74, "duration": 4.29}, {"text": "father figure psychologists all these", "start": 2865.32, "duration": 3.75}, {"text": "things and you know like his book of", "start": 2867.03, "duration": 5.04}, {"text": "rules for life is wondering why you know", "start": 2869.07, "duration": 4.62}, {"text": "people in the trans form you could use", "start": 2872.07, "duration": 2.58}, {"text": "some of the things that are said that", "start": 2873.69, "duration": 2.49}, {"text": "there's nothing like there's nothing", "start": 2874.65, "duration": 3.51}, {"text": "about trans people in that book it's", "start": 2876.18, "duration": 3.81}, {"text": "it's it's a book about how to make your", "start": 2878.16, "duration": 3.36}, {"text": "life better and why they're not willing", "start": 2879.99, "duration": 3.96}, {"text": "to say the there isn't that connection", "start": 2881.52, "duration": 4.29}, {"text": "and though I don't know I mean I don't", "start": 2883.95, "duration": 4.17}, {"text": "know how to make who it is because I", "start": 2885.81, "duration": 4.5}, {"text": "don't know I'm not in that community I", "start": 2888.12, "duration": 4.41}, {"text": "you know I think that there's a lot of", "start": 2890.31, "duration": 3.48}, {"text": "people that are very vocal in that", "start": 2892.53, "duration": 3.06}, {"text": "community which don't send represent the", "start": 2893.79, "duration": 3.48}, {"text": "whole community there are people who are", "start": 2895.59, "duration": 3.51}, {"text": "just doing their thing and they're just", "start": 2897.27, "duration": 3.51}, {"text": "trying to live their lives so it's like", "start": 2899.1, "duration": 3.23}, {"text": "I don't I don't have that quick at that", "start": 2900.78, "duration": 3.75}, {"text": "so maybe so maybe this could be the last", "start": 2902.33, "duration": 3.4}, {"text": "one because I saw the guy from the", "start": 2904.53, "duration": 15.09}, {"text": "cinema come in look at me oh yeah oh so", "start": 2905.73, "duration": 15.36}, {"text": "maybe I can make an announcement too", "start": 2919.62, "duration": 5.52}, {"text": "especially 12 Alessa across the street", "start": 2921.09, "duration": 8.16}, {"text": "so I I'm also I also cuz I done doing", "start": 2925.14, "duration": 6.69}, {"text": "this YouTube thing and it's I feel like", "start": 2929.25, "duration": 4.32}, {"text": "you know how this lady said did you need", "start": 2931.83, "duration": 3.75}, {"text": "to do real people think so what I want", "start": 2933.57, "duration": 4.32}, {"text": "to start doing is I also want to start", "start": 2935.58, "duration": 4.95}, {"text": "to organize some kind of discussion in", "start": 2937.89, "duration": 3.51}, {"text": "French", "start": 2940.53, "duration": 4.32}, {"text": "probably so his only to Quebec so I'm", "start": 2941.4, "duration": 5.04}, {"text": "probably gonna want to do something you", "start": 2944.85, "duration": 2.91}, {"text": "guys all the only speaking people", "start": 2946.44, "duration": 3.21}, {"text": "getting to find all kinds of special but", "start": 2947.76, "duration": 3.36}, {"text": "I probably wanted to start a French", "start": 2949.65, "duration": 3.24}, {"text": "speaking kind of discussion group to", "start": 2951.12, "duration": 4.14}, {"text": "talk about about a lot of the issues", "start": 2952.89, "duration": 3.36}, {"text": "that George bring it up about", "start": 2955.26, "duration": 3.18}, {"text": "spirituality about you know even", "start": 2956.25, "duration": 3.68}, {"text": "politics I'm not a big", "start": 2958.44, "duration": 3.38}, {"text": "we can talk about politics too so if", "start": 2959.93, "duration": 4.56}, {"text": "you're interested in that possibility", "start": 2961.82, "duration": 5.58}, {"text": "you can write me I have my business", "start": 2964.49, "duration": 4.35}, {"text": "cards you I can give you a card you can", "start": 2967.4, "duration": 3.06}, {"text": "write me an email and I'll try to just", "start": 2968.84, "duration": 3.24}, {"text": "set something up for those who are", "start": 2970.46, "duration": 3.63}, {"text": "interested in that maybe hopefully even", "start": 2972.08, "duration": 3.81}, {"text": "starting next month so if you're", "start": 2974.09, "duration": 2.61}, {"text": "interested in that kind of discussion", "start": 2975.89, "duration": 4.38}, {"text": "you can come up see me and all right", "start": 2976.7, "duration": 10.2}, {"text": "guys thank you for coming if you enjoy", "start": 2980.27, "duration": 8.46}, {"text": "the symbolic world content there's a lot", "start": 2986.9, "duration": 3.66}, {"text": "of things you can do to help us out and", "start": 2988.73, "duration": 4.23}, {"text": "not subscribe please do go ahead and", "start": 2990.56, "duration": 4.44}, {"text": "share this to all your friends if you", "start": 2992.96, "duration": 4.2}, {"text": "can get involved in the discussion we", "start": 2995.0, "duration": 3.9}, {"text": "have a Facebook group in which people", "start": 2997.16, "duration": 3.99}, {"text": "can talk about these subjects I will put", "start": 2998.9, "duration": 3.84}, {"text": "all those links in the description and", "start": 3001.15, "duration": 4.02}, {"text": "also if you can please support us", "start": 3002.74, "duration": 5.69}, {"text": "financially by going to my website", "start": 3005.17, "duration": 3.26}, {"text": "www.jfn.co.jp/toho", "start": 3013.89, "duration": 3.0}]}