{
 "video_id": "yH5RTxuI6SE",
 "channel_id": "UC8SErJkYnDsYGh1HxoZkl-g",
 "channel_name": "Michael Sartori",
 "title": "The Desacralization of Slides",
 "url": "https://www.youtube.com/watch?v=yH5RTxuI6SE",
 "date": "2023-02-28",
 "description": "",
 "duration": 35,
 "transcript_parts": [
  {
   "text": "eating hierarchy so when you make when",
   "start": 0.0,
   "duration": 6.42
  },
  {
   "text": "you make a soup can",
   "start": 3.36,
   "duration": 4.86
  },
  {
   "text": "you have to consider the materials",
   "start": 6.42,
   "duration": 3.24
  },
  {
   "text": "you're making based on the purpose that",
   "start": 8.22,
   "duration": 4.26
  },
  {
   "text": "it has and so if Andy Warhol can make a",
   "start": 9.66,
   "duration": 6.539
  },
  {
   "text": "screen print of a soup can and it's kind",
   "start": 12.48,
   "duration": 6.24
  },
  {
   "text": "of arbitrary maybe not completely but",
   "start": 16.199,
   "duration": 5.221
  },
  {
   "text": "kind of then once they take Andy",
   "start": 18.72,
   "duration": 4.2
  },
  {
   "text": "warhol's",
   "start": 21.42,
   "duration": 3.54
  },
  {
   "text": "um design and they make it a soup can",
   "start": 22.92,
   "duration": 3.66
  },
  {
   "text": "out of it then they have to make the",
   "start": 24.96,
   "duration": 4.26
  },
  {
   "text": "soup can out of aluminum or tin they",
   "start": 26.58,
   "duration": 5.039
  },
  {
   "text": "have to make the paper out of of paper",
   "start": 29.22,
   "duration": 4.2
  },
  {
   "text": "you know they have to put the soup",
   "start": 31.619,
   "duration": 4.641
  },
  {
   "text": "inside the can",
   "start": 33.42,
   "duration": 2.84
  }
 ]
}